[
    {
        "id": "A5",
        "max_point": null,
        "average_points": null,
        "Budapest": null,
        "Közép-Dunántúl": null,
        "Pest megye": null,
        "Nyugat-Dunántúl": null,
        "Észak-Magyarország": null,
        "Dél-Alföld": null,
        "Észak-Alföld": null,
        "Dél-Dunántúl": null,
        "Szálláshely szolgálatatás, vendéglátás": null,
        "Építőipar": null,
        "Pénzügyi, biztosítási tevékenység": null,
        "Adminisztratív és szolgáltatást támogató tevékenység": null,
        "Kereskedelem, gépjárműjavítás": null,
        "Ingatlanügyek": null,
        "Feldolgozóipar": null,
        "Információ, kommunikáció": null,
        "Egyéb (közigazgatás, oktatás, egészségügy, szociális ellátás, művészet, egyéb szolgáltatás)": null,
        "Szakmai, tudományos, műszaki tevékenység, könyvelés": null,
        "Villamosenergia-, gáz-, gőzellátás, légkondicionálás, vízellátás": null,
        "Szállítás\/raktározás": null,
        "Mezőgazdaság, bányászat": null,
        "5-9 fő": null,
        "20-49 fő": null,
        "10-19 fő": null,
        "50-249 fő": null,
        "Informatikai eszközt használó munkavállalók": null
    },
    {
        "id": "A6",
        "max_point": 8.0,
        "average_points": 6.2657807309,
        "Budapest": 6.6666666667,
        "Közép-Dunántúl": 5.8518518519,
        "Pest megye": 6.3193277311,
        "Nyugat-Dunántúl": 6.3846153846,
        "Észak-Magyarország": 5.756097561,
        "Dél-Alföld": 5.7230769231,
        "Észak-Alföld": 6.2666666667,
        "Dél-Dunántúl": 6.2,
        "Szálláshely szolgálatatás, vendéglátás": 5.7297297297,
        "Építőipar": 6.0769230769,
        "Pénzügyi, biztosítási tevékenység": 7.6923076923,
        "Adminisztratív és szolgáltatást támogató tevékenység": 6.0540540541,
        "Kereskedelem, gépjárműjavítás": 6.8157894737,
        "Ingatlanügyek": 8.0,
        "Feldolgozóipar": 6.0317460317,
        "Információ, kommunikáció": 5.3333333333,
        "Egyéb (közigazgatás, oktatás, egészségügy, szociális ellátás, művészet, egyéb szolgáltatás)": 6.1818181818,
        "Szakmai, tudományos, műszaki tevékenység, könyvelés": 5.6,
        "Villamosenergia-, gáz-, gőzellátás, légkondicionálás, vízellátás": 6.6666666667,
        "Szállítás\/raktározás": 4.25,
        "Mezőgazdaság, bányászat": 6.4347826087,
        "5-9 fő": 5.8056426332,
        "20-49 fő": 7.0697674419,
        "10-19 fő": 6.5569620253,
        "50-249 fő": 7.0769230769,
        "Informatikai eszközt használó munkavállalók": null
    },
    {
        "id": "A7",
        "max_point": null,
        "average_points": 9.792358804,
        "Budapest": 13.8947368421,
        "Közép-Dunántúl": 10.037037037,
        "Pest megye": 8.025210084,
        "Nyugat-Dunántúl": 7.3076923077,
        "Észak-Magyarország": 8.0243902439,
        "Dél-Alföld": 9.5076923077,
        "Észak-Alföld": 7.7666666667,
        "Dél-Dunántúl": 5.725,
        "Szálláshely szolgálatatás, vendéglátás": 7.3783783784,
        "Építőipar": 6.3269230769,
        "Pénzügyi, biztosítási tevékenység": 13.5384615385,
        "Adminisztratív és szolgáltatást támogató tevékenység": 10.972972973,
        "Kereskedelem, gépjárműjavítás": 11.0131578947,
        "Ingatlanügyek": 17.5,
        "Feldolgozóipar": 8.4285714286,
        "Információ, kommunikáció": 11.5,
        "Egyéb (közigazgatás, oktatás, egészségügy, szociális ellátás, művészet, egyéb szolgáltatás)": 11.9090909091,
        "Szakmai, tudományos, műszaki tevékenység, könyvelés": 7.9333333333,
        "Villamosenergia-, gáz-, gőzellátás, légkondicionálás, vízellátás": 5.6666666667,
        "Szállítás\/raktározás": 13.1875,
        "Mezőgazdaság, bányászat": 7.8695652174,
        "5-9 fő": 4.2915360502,
        "20-49 fő": 15.9534883721,
        "10-19 fő": 8.1772151899,
        "50-249 fő": 47.7435897436,
        "Informatikai eszközt használó munkavállalók": 9.792358804
    },
    {
        "id": "A8",
        "max_point": 6.0,
        "average_points": 1.6024305556,
        "Budapest": 3.6467065868,
        "Közép-Dunántúl": 0.3,
        "Pest megye": 1.0973451327,
        "Nyugat-Dunántúl": 1.1730769231,
        "Észak-Magyarország": 0.1707317073,
        "Dél-Alföld": 0.9833333333,
        "Észak-Alföld": 0.25,
        "Dél-Dunántúl": 0.9189189189,
        "Szálláshely szolgálatatás, vendéglátás": 0.34375,
        "Építőipar": 0.3958333333,
        "Pénzügyi, biztosítási tevékenység": 7.3076923077,
        "Adminisztratív és szolgáltatást támogató tevékenység": 2.0857142857,
        "Kereskedelem, gépjárműjavítás": 0.9205298013,
        "Ingatlanügyek": 0.0,
        "Feldolgozóipar": 0.4237288136,
        "Információ, kommunikáció": 9.0,
        "Egyéb (közigazgatás, oktatás, egészségügy, szociális ellátás, művészet, egyéb szolgáltatás)": 3.4537815126,
        "Szakmai, tudományos, műszaki tevékenység, könyvelés": 2.2666666667,
        "Villamosenergia-, gáz-, gőzellátás, légkondicionálás, vízellátás": 0.4444444444,
        "Szállítás\/raktározás": 1.2,
        "Mezőgazdaság, bányászat": 1.05,
        "5-9 fő": 0.8518518519,
        "20-49 fő": 2.5421686747,
        "10-19 fő": 1.6687898089,
        "50-249 fő": 5.0512820513,
        "Informatikai eszközt használó munkavállalók": null
    },
    {
        "id": "B10",
        "max_point": 25.0,
        "average_points": 9.8504983389,
        "Budapest": 11.9005847953,
        "Közép-Dunántúl": 8.4259259259,
        "Pest megye": 9.5378151261,
        "Nyugat-Dunántúl": 10.0,
        "Észak-Magyarország": 7.6829268293,
        "Dél-Alföld": 8.2307692308,
        "Észak-Alföld": 9.4166666667,
        "Dél-Dunántúl": 9.25,
        "Szálláshely szolgálatatás, vendéglátás": 12.2972972973,
        "Építőipar": 7.8846153846,
        "Pénzügyi, biztosítási tevékenység": 5.7692307692,
        "Adminisztratív és szolgáltatást támogató tevékenység": 10.8108108108,
        "Kereskedelem, gépjárműjavítás": 10.7565789474,
        "Ingatlanügyek": 5.8333333333,
        "Feldolgozóipar": 8.4126984127,
        "Információ, kommunikáció": 17.5,
        "Egyéb (közigazgatás, oktatás, egészségügy, szociális ellátás, művészet, egyéb szolgáltatás)": 11.0330578512,
        "Szakmai, tudományos, műszaki tevékenység, könyvelés": 8.0,
        "Villamosenergia-, gáz-, gőzellátás, légkondicionálás, vízellátás": 8.3333333333,
        "Szállítás\/raktározás": 10.3125,
        "Mezőgazdaság, bányászat": 7.8260869565,
        "5-9 fő": 8.8401253918,
        "20-49 fő": 11.0465116279,
        "10-19 fő": 10.7911392405,
        "50-249 fő": 11.6666666667,
        "Informatikai eszközt használó munkavállalók": null
    },
    {
        "id": "B11",
        "max_point": 15.0,
        "average_points": 2.025,
        "Budapest": 2.303030303,
        "Közép-Dunántúl": 1.25,
        "Pest megye": 2.0491803279,
        "Nyugat-Dunántúl": 1.3548387097,
        "Észak-Magyarország": 1.5882352941,
        "Dél-Alföld": 2.65625,
        "Észak-Alföld": 1.8,
        "Dél-Dunántúl": 2.2857142857,
        "Szálláshely szolgálatatás, vendéglátás": 2.7333333333,
        "Építőipar": 1.2307692308,
        "Pénzügyi, biztosítási tevékenység": 0.5,
        "Adminisztratív és szolgáltatást támogató tevékenység": 2.5454545455,
        "Kereskedelem, gépjárműjavítás": 2.2446808511,
        "Ingatlanügyek": 2.5,
        "Feldolgozóipar": 1.4166666667,
        "Információ, kommunikáció": 2.2,
        "Egyéb (közigazgatás, oktatás, egészségügy, szociális ellátás, művészet, egyéb szolgáltatás)": 2.1756756757,
        "Szakmai, tudományos, műszaki tevékenység, könyvelés": 0.0,
        "Villamosenergia-, gáz-, gőzellátás, légkondicionálás, vízellátás": 2.0,
        "Szállítás\/raktározás": 0.8571428571,
        "Mezőgazdaság, bányászat": 3.0,
        "5-9 fő": 1.82,
        "20-49 fő": 2.2407407407,
        "10-19 fő": 2.0744680851,
        "50-249 fő": 2.6818181818,
        "Informatikai eszközt használó munkavállalók": null
    },
    {
        "id": "B12",
        "max_point": 15.0,
        "average_points": 1.5415282392,
        "Budapest": 1.9649122807,
        "Közép-Dunántúl": 0.8888888889,
        "Pest megye": 1.6134453782,
        "Nyugat-Dunántúl": 1.6923076923,
        "Észak-Magyarország": 1.9512195122,
        "Dél-Alföld": 0.9846153846,
        "Észak-Alföld": 1.0666666667,
        "Dél-Dunántúl": 1.4,
        "Szálláshely szolgálatatás, vendéglátás": 1.5135135135,
        "Építőipar": 0.9230769231,
        "Pénzügyi, biztosítási tevékenység": 3.6923076923,
        "Adminisztratív és szolgáltatást támogató tevékenység": 1.7297297297,
        "Kereskedelem, gépjárműjavítás": 1.2631578947,
        "Ingatlanügyek": 0.0,
        "Feldolgozóipar": 2.0317460317,
        "Információ, kommunikáció": 2.6666666667,
        "Egyéb (közigazgatás, oktatás, egészségügy, szociális ellátás, művészet, egyéb szolgáltatás)": 2.3140495868,
        "Szakmai, tudományos, műszaki tevékenység, könyvelés": 1.6,
        "Villamosenergia-, gáz-, gőzellátás, légkondicionálás, vízellátás": 0.0,
        "Szállítás\/raktározás": 0.5,
        "Mezőgazdaság, bányászat": 0.6956521739,
        "5-9 fő": 1.3542319749,
        "20-49 fő": 1.5813953488,
        "10-19 fő": 1.5189873418,
        "50-249 fő": 3.0769230769,
        "Informatikai eszközt használó munkavállalók": null
    },
    {
        "id": "B13",
        "max_point": 16.0,
        "average_points": 4.8621262458,
        "Budapest": 5.5847953216,
        "Közép-Dunántúl": 2.9444444444,
        "Pest megye": 5.4285714286,
        "Nyugat-Dunántúl": 4.2307692308,
        "Észak-Magyarország": 4.7317073171,
        "Dél-Alföld": 5.2615384615,
        "Észak-Alföld": 4.5333333333,
        "Dél-Dunántúl": 3.475,
        "Szálláshely szolgálatatás, vendéglátás": 2.3513513514,
        "Építőipar": 3.4230769231,
        "Pénzügyi, biztosítási tevékenység": 5.2307692308,
        "Adminisztratív és szolgáltatást támogató tevékenység": 4.5405405405,
        "Kereskedelem, gépjárműjavítás": 6.6381578947,
        "Ingatlanügyek": 9.1666666667,
        "Feldolgozóipar": 4.9682539683,
        "Információ, kommunikáció": 4.8333333333,
        "Egyéb (közigazgatás, oktatás, egészségügy, szociális ellátás, művészet, egyéb szolgáltatás)": 4.5289256198,
        "Szakmai, tudományos, műszaki tevékenység, könyvelés": 3.8666666667,
        "Villamosenergia-, gáz-, gőzellátás, légkondicionálás, vízellátás": 7.2222222222,
        "Szállítás\/raktározás": 4.4375,
        "Mezőgazdaság, bányászat": 4.347826087,
        "5-9 fő": 3.8181818182,
        "20-49 fő": 6.8488372093,
        "10-19 fő": 4.9493670886,
        "50-249 fő": 8.6666666667,
        "Informatikai eszközt használó munkavállalók": null
    },
    {
        "id": "B14",
        "max_point": 26.0,
        "average_points": 15.4584717608,
        "Budapest": 18.0116959064,
        "Közép-Dunántúl": 9.3888888889,
        "Pest megye": 16.8739495798,
        "Nyugat-Dunántúl": 13.4230769231,
        "Észak-Magyarország": 17.8292682927,
        "Dél-Alföld": 17.4307692308,
        "Észak-Alföld": 13.6666666667,
        "Dél-Dunántúl": 8.225,
        "Szálláshely szolgálatatás, vendéglátás": 6.5405405405,
        "Építőipar": 10.4230769231,
        "Pénzügyi, biztosítási tevékenység": 16.4615384615,
        "Adminisztratív és szolgáltatást támogató tevékenység": 8.5945945946,
        "Kereskedelem, gépjárműjavítás": 21.375,
        "Ingatlanügyek": 19.6666666667,
        "Feldolgozóipar": 18.6666666667,
        "Információ, kommunikáció": 23.1666666667,
        "Egyéb (közigazgatás, oktatás, egészségügy, szociális ellátás, művészet, egyéb szolgáltatás)": 15.4710743802,
        "Szakmai, tudományos, műszaki tevékenység, könyvelés": 12.7333333333,
        "Villamosenergia-, gáz-, gőzellátás, légkondicionálás, vízellátás": 24.5555555556,
        "Szállítás\/raktározás": 11.4375,
        "Mezőgazdaság, bányászat": 13.0,
        "5-9 fő": 11.4639498433,
        "20-49 fő": 23.8604651163,
        "10-19 fő": 15.5569620253,
        "50-249 fő": 29.2051282051,
        "Informatikai eszközt használó munkavállalók": null
    },
    {
        "id": "B15",
        "max_point": 26.0,
        "average_points": 38.023255814,
        "Budapest": 38.2631578947,
        "Közép-Dunántúl": 40.6111111111,
        "Pest megye": 36.7478991597,
        "Nyugat-Dunántúl": 38.9038461538,
        "Észak-Magyarország": 38.7804878049,
        "Dél-Alföld": 35.5384615385,
        "Észak-Alföld": 39.2666666667,
        "Dél-Dunántúl": 37.55,
        "Szálláshely szolgálatatás, vendéglátás": 38.5945945946,
        "Építőipar": 35.2596153846,
        "Pénzügyi, biztosítási tevékenység": 53.6923076923,
        "Adminisztratív és szolgáltatást támogató tevékenység": 38.7837837838,
        "Kereskedelem, gépjárműjavítás": 37.5657894737,
        "Ingatlanügyek": 37.1666666667,
        "Feldolgozóipar": 38.1111111111,
        "Információ, kommunikáció": 44.1666666667,
        "Egyéb (közigazgatás, oktatás, egészségügy, szociális ellátás, művészet, egyéb szolgáltatás)": 38.8925619835,
        "Szakmai, tudományos, műszaki tevékenység, könyvelés": 41.4666666667,
        "Villamosenergia-, gáz-, gőzellátás, légkondicionálás, vízellátás": 40.7777777778,
        "Szállítás\/raktározás": 34.25,
        "Mezőgazdaság, bányászat": 35.652173913,
        "5-9 fő": 35.3918495298,
        "20-49 fő": 40.6860465116,
        "10-19 fő": 40.8164556962,
        "50-249 fő": 42.358974359,
        "Informatikai eszközt használó munkavállalók": null
    },
    {
        "id": "B16",
        "max_point": 23.0,
        "average_points": 2.0980066445,
        "Budapest": 2.6549707602,
        "Közép-Dunántúl": 1.5185185185,
        "Pest megye": 2.2521008403,
        "Nyugat-Dunántúl": 2.2115384615,
        "Észak-Magyarország": 1.512195122,
        "Dél-Alföld": 1.3230769231,
        "Észak-Alföld": 1.8166666667,
        "Dél-Dunántúl": 2.175,
        "Szálláshely szolgálatatás, vendéglátás": 3.1351351351,
        "Építőipar": 2.4038461538,
        "Pénzügyi, biztosítási tevékenység": 5.2307692308,
        "Adminisztratív és szolgáltatást támogató tevékenység": 2.6486486486,
        "Kereskedelem, gépjárműjavítás": 1.625,
        "Ingatlanügyek": 0.8333333333,
        "Feldolgozóipar": 1.4603174603,
        "Információ, kommunikáció": 3.1666666667,
        "Egyéb (közigazgatás, oktatás, egészségügy, szociális ellátás, művészet, egyéb szolgáltatás)": 2.4132231405,
        "Szakmai, tudományos, műszaki tevékenység, könyvelés": 1.8666666667,
        "Villamosenergia-, gáz-, gőzellátás, légkondicionálás, vízellátás": 1.0,
        "Szállítás\/raktározás": 1.75,
        "Mezőgazdaság, bányászat": 0.4782608696,
        "5-9 fő": 1.9059561129,
        "20-49 fő": 2.1744186047,
        "10-19 fő": 2.4430379747,
        "50-249 fő": 2.1025641026,
        "Informatikai eszközt használó munkavállalók": null
    },
    {
        "id": "B17_1",
        "max_point": 4.0,
        "average_points": 0.3333333333,
        "Budapest": 0.7185628743,
        "Közép-Dunántúl": 0.0,
        "Pest megye": 0.1769911504,
        "Nyugat-Dunántúl": 0.1538461538,
        "Észak-Magyarország": 0.3902439024,
        "Dél-Alföld": 0.2,
        "Észak-Alföld": 0.0714285714,
        "Dél-Dunántúl": 0.3243243243,
        "Szálláshely szolgálatatás, vendéglátás": 0.375,
        "Építőipar": 0.25,
        "Pénzügyi, biztosítási tevékenység": 0.3076923077,
        "Adminisztratív és szolgáltatást támogató tevékenység": 0.4571428571,
        "Kereskedelem, gépjárműjavítás": 0.2119205298,
        "Ingatlanügyek": 0.6666666667,
        "Feldolgozóipar": 0.3389830508,
        "Információ, kommunikáció": 0.6666666667,
        "Egyéb (közigazgatás, oktatás, egészségügy, szociális ellátás, művészet, egyéb szolgáltatás)": 0.5714285714,
        "Szakmai, tudományos, műszaki tevékenység, könyvelés": 0.0,
        "Villamosenergia-, gáz-, gőzellátás, légkondicionálás, vízellátás": 0.0,
        "Szállítás\/raktározás": 0.2666666667,
        "Mezőgazdaság, bányászat": 0.2,
        "5-9 fő": 0.2424242424,
        "20-49 fő": 0.4819277108,
        "10-19 fő": 0.3312101911,
        "50-249 fő": 0.7179487179,
        "Informatikai eszközt használó munkavállalók": null
    },
    {
        "id": "B17_2",
        "max_point": 4.0,
        "average_points": 2.1805555556,
        "Budapest": 2.5628742515,
        "Közép-Dunántúl": 1.92,
        "Pest megye": 2.3008849558,
        "Nyugat-Dunántúl": 2.3846153846,
        "Észak-Magyarország": 1.4634146341,
        "Dél-Alföld": 1.9333333333,
        "Észak-Alföld": 2.0714285714,
        "Dél-Dunántúl": 1.5135135135,
        "Szálláshely szolgálatatás, vendéglátás": 2.25,
        "Építőipar": 1.7083333333,
        "Pénzügyi, biztosítási tevékenység": 2.7692307692,
        "Adminisztratív és szolgáltatást támogató tevékenység": 2.5142857143,
        "Kereskedelem, gépjárműjavítás": 2.1721854305,
        "Ingatlanügyek": 2.0,
        "Feldolgozóipar": 1.8983050847,
        "Információ, kommunikáció": 4.0,
        "Egyéb (közigazgatás, oktatás, egészségügy, szociális ellátás, művészet, egyéb szolgáltatás)": 2.3529411765,
        "Szakmai, tudományos, műszaki tevékenység, könyvelés": 3.4666666667,
        "Villamosenergia-, gáz-, gőzellátás, légkondicionálás, vízellátás": 3.1111111111,
        "Szállítás\/raktározás": 1.6,
        "Mezőgazdaság, bányászat": 1.8,
        "5-9 fő": 1.9259259259,
        "20-49 fő": 2.6506024096,
        "10-19 fő": 2.2675159236,
        "50-249 fő": 2.7692307692,
        "Informatikai eszközt használó munkavállalók": null
    },
    {
        "id": "B17_3",
        "max_point": 4.0,
        "average_points": 1.7777777778,
        "Budapest": 2.3952095808,
        "Közép-Dunántúl": 1.6,
        "Pest megye": 1.6283185841,
        "Nyugat-Dunántúl": 1.6153846154,
        "Észak-Magyarország": 1.0731707317,
        "Dél-Alföld": 1.4666666667,
        "Észak-Alföld": 1.7857142857,
        "Dél-Dunántúl": 1.1891891892,
        "Szálláshely szolgálatatás, vendéglátás": 1.25,
        "Építőipar": 1.5,
        "Pénzügyi, biztosítási tevékenység": 2.4615384615,
        "Adminisztratív és szolgáltatást támogató tevékenység": 2.1714285714,
        "Kereskedelem, gépjárműjavítás": 1.4569536424,
        "Ingatlanügyek": 2.0,
        "Feldolgozóipar": 1.6949152542,
        "Információ, kommunikáció": 3.3333333333,
        "Egyéb (közigazgatás, oktatás, egészségügy, szociális ellátás, művészet, egyéb szolgáltatás)": 2.1512605042,
        "Szakmai, tudományos, műszaki tevékenység, könyvelés": 2.9333333333,
        "Villamosenergia-, gáz-, gőzellátás, légkondicionálás, vízellátás": 1.7777777778,
        "Szállítás\/raktározás": 1.6,
        "Mezőgazdaság, bányászat": 2.0,
        "5-9 fő": 1.468013468,
        "20-49 fő": 2.1686746988,
        "10-19 fő": 1.8598726115,
        "50-249 fő": 2.9743589744,
        "Informatikai eszközt használó munkavállalók": null
    },
    {
        "id": "B1_3",
        "max_point": 15.0,
        "average_points": 5.1079734219,
        "Budapest": 5.5263157895,
        "Közép-Dunántúl": 5.0,
        "Pest megye": 5.2941176471,
        "Nyugat-Dunántúl": 4.6153846154,
        "Észak-Magyarország": 7.6829268293,
        "Dél-Alföld": 4.3846153846,
        "Észak-Alföld": 3.0,
        "Dél-Dunántúl": 5.25,
        "Szálláshely szolgálatatás, vendéglátás": 7.2972972973,
        "Építőipar": 3.75,
        "Pénzügyi, biztosítási tevékenység": 4.6153846154,
        "Adminisztratív és szolgáltatást támogató tevékenység": 5.2702702703,
        "Kereskedelem, gépjárműjavítás": 5.7236842105,
        "Ingatlanügyek": 5.0,
        "Feldolgozóipar": 5.4761904762,
        "Információ, kommunikáció": 7.5,
        "Egyéb (közigazgatás, oktatás, egészségügy, szociális ellátás, művészet, egyéb szolgáltatás)": 5.3305785124,
        "Szakmai, tudományos, műszaki tevékenység, könyvelés": 2.0,
        "Villamosenergia-, gáz-, gőzellátás, légkondicionálás, vízellátás": 6.6666666667,
        "Szállítás\/raktározás": 3.75,
        "Mezőgazdaság, bányászat": 3.2608695652,
        "5-9 fő": 4.7962382445,
        "20-49 fő": 4.5348837209,
        "10-19 fő": 6.3607594937,
        "50-249 fő": 3.8461538462,
        "Informatikai eszközt használó munkavállalók": null
    },
    {
        "id": "B1_1",
        "max_point": 15.0,
        "average_points": 10.8139534884,
        "Budapest": 12.7192982456,
        "Közép-Dunántúl": 10.8333333333,
        "Pest megye": 11.0924369748,
        "Nyugat-Dunántúl": 9.2307692308,
        "Észak-Magyarország": 9.512195122,
        "Dél-Alföld": 9.6923076923,
        "Észak-Alföld": 9.0,
        "Dél-Dunántúl": 9.75,
        "Szálláshely szolgálatatás, vendéglátás": 12.5675675676,
        "Építőipar": 8.9423076923,
        "Pénzügyi, biztosítási tevékenység": 9.2307692308,
        "Adminisztratív és szolgáltatást támogató tevékenység": 10.5405405405,
        "Kereskedelem, gépjárműjavítás": 10.8552631579,
        "Ingatlanügyek": 12.5,
        "Feldolgozóipar": 11.1904761905,
        "Információ, kommunikáció": 15.0,
        "Egyéb (közigazgatás, oktatás, egészségügy, szociális ellátás, művészet, egyéb szolgáltatás)": 12.520661157,
        "Szakmai, tudományos, műszaki tevékenység, könyvelés": 12.0,
        "Villamosenergia-, gáz-, gőzellátás, légkondicionálás, vízellátás": 10.0,
        "Szállítás\/raktározás": 7.5,
        "Mezőgazdaság, bányászat": 7.8260869565,
        "5-9 fő": 10.0156739812,
        "20-49 fő": 11.8604651163,
        "10-19 fő": 11.4873417722,
        "50-249 fő": 12.3076923077,
        "Informatikai eszközt használó munkavállalók": null
    },
    {
        "id": "B1_2",
        "max_point": 5.0,
        "average_points": 0.5149501661,
        "Budapest": 0.6140350877,
        "Közép-Dunántúl": 0.2777777778,
        "Pest megye": 0.7142857143,
        "Nyugat-Dunántúl": 0.1923076923,
        "Észak-Magyarország": 0.3658536585,
        "Dél-Alföld": 0.5384615385,
        "Észak-Alföld": 0.5,
        "Dél-Dunántúl": 0.375,
        "Szálláshely szolgálatatás, vendéglátás": 0.4054054054,
        "Építőipar": 0.0480769231,
        "Pénzügyi, biztosítási tevékenység": 0.0,
        "Adminisztratív és szolgáltatást támogató tevékenység": 0.2702702703,
        "Kereskedelem, gépjárműjavítás": 1.25,
        "Ingatlanügyek": 0.0,
        "Feldolgozóipar": 0.6349206349,
        "Információ, kommunikáció": 0.8333333333,
        "Egyéb (közigazgatás, oktatás, egészségügy, szociális ellátás, művészet, egyéb szolgáltatás)": 0.1652892562,
        "Szakmai, tudományos, műszaki tevékenység, könyvelés": 0.3333333333,
        "Villamosenergia-, gáz-, gőzellátás, légkondicionálás, vízellátás": 0.5555555556,
        "Szállítás\/raktározás": 0.3125,
        "Mezőgazdaság, bányászat": 0.4347826087,
        "5-9 fő": 0.407523511,
        "20-49 fő": 0.7558139535,
        "10-19 fő": 0.5063291139,
        "50-249 fő": 0.8974358974,
        "Informatikai eszközt használó munkavállalók": null
    },
    {
        "id": "B2",
        "max_point": 15.0,
        "average_points": 13.9516129032,
        "Budapest": 14.1793103448,
        "Közép-Dunántúl": 13.3846153846,
        "Pest megye": 13.8863636364,
        "Nyugat-Dunántúl": 14.34375,
        "Észak-Magyarország": 13.9230769231,
        "Dél-Alföld": 13.8333333333,
        "Észak-Alföld": 13.6388888889,
        "Dél-Dunántúl": 13.9230769231,
        "Szálláshely szolgálatatás, vendéglátás": 13.8709677419,
        "Építőipar": 13.5322580645,
        "Pénzügyi, biztosítási tevékenység": 12.375,
        "Adminisztratív és szolgáltatást támogató tevékenység": 13.6538461538,
        "Kereskedelem, gépjárműjavítás": 14.0454545455,
        "Ingatlanügyek": 15.0,
        "Feldolgozóipar": 14.2553191489,
        "Információ, kommunikáció": 13.8333333333,
        "Egyéb (közigazgatás, oktatás, egészségügy, szociális ellátás, művészet, egyéb szolgáltatás)": 14.1683168317,
        "Szakmai, tudományos, műszaki tevékenység, könyvelés": 15.0,
        "Villamosenergia-, gáz-, gőzellátás, légkondicionálás, vízellátás": 12.6666666667,
        "Szállítás\/raktározás": 15.0,
        "Mezőgazdaság, bányászat": 12.6666666667,
        "5-9 fő": 13.882629108,
        "20-49 fő": 13.8676470588,
        "10-19 fő": 14.0165289256,
        "50-249 fő": 14.34375,
        "Informatikai eszközt használó munkavállalók": null
    },
    {
        "id": "B3",
        "max_point": 15.0,
        "average_points": 6.7903225806,
        "Budapest": 6.8275862069,
        "Közép-Dunántúl": 6.2564102564,
        "Pest megye": 6.1704545455,
        "Nyugat-Dunántúl": 9.25,
        "Észak-Magyarország": 6.4230769231,
        "Dél-Alföld": 6.7142857143,
        "Észak-Alföld": 7.6666666667,
        "Dél-Dunántúl": 5.7307692308,
        "Szálláshely szolgálatatás, vendéglátás": 8.6451612903,
        "Építőipar": 4.9516129032,
        "Pénzügyi, biztosítási tevékenység": 4.625,
        "Adminisztratív és szolgáltatást támogató tevékenység": 7.3846153846,
        "Kereskedelem, gépjárműjavítás": 8.1272727273,
        "Ingatlanügyek": 6.4,
        "Feldolgozóipar": 4.6595744681,
        "Információ, kommunikáció": 8.5,
        "Egyéb (közigazgatás, oktatás, egészségügy, szociális ellátás, művészet, egyéb szolgáltatás)": 7.3762376238,
        "Szakmai, tudományos, műszaki tevékenység, könyvelés": 4.9166666667,
        "Villamosenergia-, gáz-, gőzellátás, légkondicionálás, vízellátás": 4.6666666667,
        "Szállítás\/raktározás": 3.75,
        "Mezőgazdaság, bányászat": 7.0833333333,
        "5-9 fő": 6.103286385,
        "20-49 fő": 8.75,
        "10-19 fő": 6.9090909091,
        "50-249 fő": 6.75,
        "Informatikai eszközt használó munkavállalók": null
    },
    {
        "id": "B4",
        "max_point": 15.0,
        "average_points": 5.0,
        "Budapest": 5.0,
        "Közép-Dunántúl": null,
        "Pest megye": 5.0,
        "Nyugat-Dunántúl": null,
        "Észak-Magyarország": null,
        "Dél-Alföld": 5.0,
        "Észak-Alföld": null,
        "Dél-Dunántúl": null,
        "Szálláshely szolgálatatás, vendéglátás": null,
        "Építőipar": null,
        "Pénzügyi, biztosítási tevékenység": null,
        "Adminisztratív és szolgáltatást támogató tevékenység": null,
        "Kereskedelem, gépjárműjavítás": 5.0,
        "Ingatlanügyek": null,
        "Feldolgozóipar": null,
        "Információ, kommunikáció": null,
        "Egyéb (közigazgatás, oktatás, egészségügy, szociális ellátás, művészet, egyéb szolgáltatás)": null,
        "Szakmai, tudományos, műszaki tevékenység, könyvelés": null,
        "Villamosenergia-, gáz-, gőzellátás, légkondicionálás, vízellátás": null,
        "Szállítás\/raktározás": null,
        "Mezőgazdaság, bányászat": null,
        "5-9 fő": 5.0,
        "20-49 fő": null,
        "10-19 fő": 5.0,
        "50-249 fő": 5.0,
        "Informatikai eszközt használó munkavállalók": null
    },
    {
        "id": "B5a_2",
        "max_point": 7.0,
        "average_points": 0.2211981567,
        "Budapest": 0.1931034483,
        "Közép-Dunántúl": 0.2051282051,
        "Pest megye": 0.2727272727,
        "Nyugat-Dunántúl": 0.375,
        "Észak-Magyarország": 0.1538461538,
        "Dél-Alföld": 0.1904761905,
        "Észak-Alföld": 0.2222222222,
        "Dél-Dunántúl": 0.1538461538,
        "Szálláshely szolgálatatás, vendéglátás": 0.1290322581,
        "Építőipar": 0.1290322581,
        "Pénzügyi, biztosítási tevékenység": 0.0,
        "Adminisztratív és szolgáltatást támogató tevékenység": 0.0,
        "Kereskedelem, gépjárműjavítás": 0.4,
        "Ingatlanügyek": 0.0,
        "Feldolgozóipar": 0.2553191489,
        "Információ, kommunikáció": 0.0,
        "Egyéb (közigazgatás, oktatás, egészségügy, szociális ellátás, művészet, egyéb szolgáltatás)": 0.198019802,
        "Szakmai, tudományos, műszaki tevékenység, könyvelés": 0.0,
        "Villamosenergia-, gáz-, gőzellátás, légkondicionálás, vízellátás": 0.6666666667,
        "Szállítás\/raktározás": 0.5,
        "Mezőgazdaság, bányászat": 0.0,
        "5-9 fő": 0.1690140845,
        "20-49 fő": 0.2941176471,
        "10-19 fő": 0.2644628099,
        "50-249 fő": 0.25,
        "Informatikai eszközt használó munkavállalók": null
    },
    {
        "id": "B5a_1",
        "max_point": 7.0,
        "average_points": 3.5023041475,
        "Budapest": 3.6137931034,
        "Közép-Dunántúl": 3.2820512821,
        "Pest megye": 3.5454545455,
        "Nyugat-Dunántúl": 3.375,
        "Észak-Magyarország": 3.3846153846,
        "Dél-Alföld": 3.619047619,
        "Észak-Alföld": 3.3333333333,
        "Dél-Dunántúl": 3.3846153846,
        "Szálláshely szolgálatatás, vendéglátás": 3.7419354839,
        "Építőipar": 3.6129032258,
        "Pénzügyi, biztosítási tevékenység": 3.5,
        "Adminisztratív és szolgáltatást támogató tevékenység": 3.6923076923,
        "Kereskedelem, gépjárműjavítás": 3.2363636364,
        "Ingatlanügyek": 3.2,
        "Feldolgozóipar": 3.4893617021,
        "Információ, kommunikáció": 4.0,
        "Egyéb (közigazgatás, oktatás, egészségügy, szociális ellátás, művészet, egyéb szolgáltatás)": 3.5247524752,
        "Szakmai, tudományos, műszaki tevékenység, könyvelés": 3.6666666667,
        "Villamosenergia-, gáz-, gőzellátás, légkondicionálás, vízellátás": 4.0,
        "Szállítás\/raktározás": 4.0,
        "Mezőgazdaság, bányászat": 3.3333333333,
        "5-9 fő": 3.3427230047,
        "20-49 fő": 3.5294117647,
        "10-19 fő": 3.6363636364,
        "50-249 fő": 4.0,
        "Informatikai eszközt használó munkavállalók": null
    },
    {
        "id": "B5a_3",
        "max_point": 7.0,
        "average_points": 1.064516129,
        "Budapest": 1.0,
        "Közép-Dunántúl": 1.6666666667,
        "Pest megye": 1.0588235294,
        "Nyugat-Dunántúl": 1.0,
        "Észak-Magyarország": 1.0,
        "Dél-Alföld": 1.0,
        "Észak-Alföld": 1.1666666667,
        "Dél-Dunántúl": 1.0,
        "Szálláshely szolgálatatás, vendéglátás": 1.0,
        "Építőipar": 1.0,
        "Pénzügyi, biztosítási tevékenység": null,
        "Adminisztratív és szolgáltatást támogató tevékenység": 1.0,
        "Kereskedelem, gépjárműjavítás": 1.0526315789,
        "Ingatlanügyek": null,
        "Feldolgozóipar": 1.25,
        "Információ, kommunikáció": 1.0,
        "Egyéb (közigazgatás, oktatás, egészségügy, szociális ellátás, művészet, egyéb szolgáltatás)": 1.0,
        "Szakmai, tudományos, műszaki tevékenység, könyvelés": 1.0,
        "Villamosenergia-, gáz-, gőzellátás, légkondicionálás, vízellátás": 1.0,
        "Szállítás\/raktározás": 1.0,
        "Mezőgazdaság, bányászat": 1.0,
        "5-9 fő": 1.0769230769,
        "20-49 fő": 0.9230769231,
        "10-19 fő": 1.25,
        "50-249 fő": 0.8571428571,
        "Informatikai eszközt használó munkavállalók": null
    },
    {
        "id": "B5b_2",
        "max_point": 7.0,
        "average_points": 0.6451612903,
        "Budapest": 0.380952381,
        "Közép-Dunántúl": 1.3333333333,
        "Pest megye": 0.9411764706,
        "Nyugat-Dunántúl": 2.0,
        "Észak-Magyarország": 0.0,
        "Dél-Alföld": 0.0,
        "Észak-Alföld": 1.3333333333,
        "Dél-Dunántúl": 0.0,
        "Szálláshely szolgálatatás, vendéglátás": 1.3333333333,
        "Építőipar": 0.0,
        "Pénzügyi, biztosítási tevékenység": null,
        "Adminisztratív és szolgáltatást támogató tevékenység": 0.0,
        "Kereskedelem, gépjárműjavítás": 0.7368421053,
        "Ingatlanügyek": null,
        "Feldolgozóipar": 1.0,
        "Információ, kommunikáció": 0.0,
        "Egyéb (közigazgatás, oktatás, egészségügy, szociális ellátás, művészet, egyéb szolgáltatás)": 0.0,
        "Szakmai, tudományos, műszaki tevékenység, könyvelés": 0.0,
        "Villamosenergia-, gáz-, gőzellátás, légkondicionálás, vízellátás": 0.0,
        "Szállítás\/raktározás": 0.0,
        "Mezőgazdaság, bányászat": 0.0,
        "5-9 fő": 0.3076923077,
        "20-49 fő": 0.6153846154,
        "10-19 fő": 1.25,
        "50-249 fő": 0.5714285714,
        "Informatikai eszközt használó munkavállalók": null
    },
    {
        "id": "B5b_1",
        "max_point": 7.0,
        "average_points": 3.4838709677,
        "Budapest": 3.619047619,
        "Közép-Dunántúl": 4.0,
        "Pest megye": 3.5294117647,
        "Nyugat-Dunántúl": 2.0,
        "Észak-Magyarország": 2.6666666667,
        "Dél-Alföld": 3.4285714286,
        "Észak-Alföld": 3.3333333333,
        "Dél-Dunántúl": 4.0,
        "Szálláshely szolgálatatás, vendéglátás": 4.0,
        "Építőipar": 4.0,
        "Pénzügyi, biztosítási tevékenység": null,
        "Adminisztratív és szolgáltatást támogató tevékenység": 2.0,
        "Kereskedelem, gépjárműjavítás": 3.4736842105,
        "Ingatlanügyek": null,
        "Feldolgozóipar": 3.5,
        "Információ, kommunikáció": 4.0,
        "Egyéb (közigazgatás, oktatás, egészségügy, szociális ellátás, művészet, egyéb szolgáltatás)": 3.0,
        "Szakmai, tudományos, műszaki tevékenység, könyvelés": 4.0,
        "Villamosenergia-, gáz-, gőzellátás, légkondicionálás, vízellátás": 4.0,
        "Szállítás\/raktározás": 4.0,
        "Mezőgazdaság, bányászat": 4.0,
        "5-9 fő": 3.6923076923,
        "20-49 fő": 2.7692307692,
        "10-19 fő": 3.5,
        "50-249 fő": 4.0,
        "Informatikai eszközt használó munkavállalók": null
    },
    {
        "id": "B6a",
        "max_point": 5.0,
        "average_points": 2.7774086379,
        "Budapest": 3.1403508772,
        "Közép-Dunántúl": 3.0555555556,
        "Pest megye": 2.9579831933,
        "Nyugat-Dunántúl": 2.3269230769,
        "Észak-Magyarország": 2.5853658537,
        "Dél-Alföld": 2.3230769231,
        "Észak-Alföld": 2.4,
        "Dél-Dunántúl": 2.4,
        "Szálláshely szolgálatatás, vendéglátás": 3.1351351351,
        "Építőipar": 2.5096153846,
        "Pénzügyi, biztosítási tevékenység": 2.6923076923,
        "Adminisztratív és szolgáltatást támogató tevékenység": 3.027027027,
        "Kereskedelem, gépjárműjavítás": 2.625,
        "Ingatlanügyek": 2.5,
        "Feldolgozóipar": 2.7619047619,
        "Információ, kommunikáció": 3.6666666667,
        "Egyéb (közigazgatás, oktatás, egészségügy, szociális ellátás, művészet, egyéb szolgáltatás)": 3.3801652893,
        "Szakmai, tudományos, műszaki tevékenység, könyvelés": 2.0666666667,
        "Villamosenergia-, gáz-, gőzellátás, légkondicionálás, vízellátás": 2.3333333333,
        "Szállítás\/raktározás": 1.6875,
        "Mezőgazdaság, bányászat": 2.1739130435,
        "5-9 fő": 2.4984326019,
        "20-49 fő": 3.2558139535,
        "10-19 fő": 2.9303797468,
        "50-249 fő": 3.3846153846,
        "Informatikai eszközt használó munkavállalók": null
    },
    {
        "id": "B6b",
        "max_point": 5.0,
        "average_points": 0.0182724252,
        "Budapest": 0.0292397661,
        "Közép-Dunántúl": 0.0,
        "Pest megye": 0.0420168067,
        "Nyugat-Dunántúl": 0.0,
        "Észak-Magyarország": 0.0,
        "Dél-Alföld": 0.0153846154,
        "Észak-Alföld": 0.0,
        "Dél-Dunántúl": 0.0,
        "Szálláshely szolgálatatás, vendéglátás": 0.0,
        "Építőipar": 0.0,
        "Pénzügyi, biztosítási tevékenység": 0.0,
        "Adminisztratív és szolgáltatást támogató tevékenység": 0.0,
        "Kereskedelem, gépjárműjavítás": 0.0723684211,
        "Ingatlanügyek": 0.0,
        "Feldolgozóipar": 0.0,
        "Információ, kommunikáció": 0.0,
        "Egyéb (közigazgatás, oktatás, egészségügy, szociális ellátás, művészet, egyéb szolgáltatás)": 0.0,
        "Szakmai, tudományos, műszaki tevékenység, könyvelés": 0.0,
        "Villamosenergia-, gáz-, gőzellátás, légkondicionálás, vízellátás": 0.0,
        "Szállítás\/raktározás": 0.0,
        "Mezőgazdaság, bányászat": 0.0,
        "5-9 fő": 0.0031347962,
        "20-49 fő": 0.0,
        "10-19 fő": 0.0316455696,
        "50-249 fő": 0.1282051282,
        "Informatikai eszközt használó munkavállalók": null
    },
    {
        "id": "B7a",
        "max_point": 3.0,
        "average_points": 1.1445182724,
        "Budapest": 1.4795321637,
        "Közép-Dunántúl": 1.1296296296,
        "Pest megye": 1.1596638655,
        "Nyugat-Dunántúl": 1.0192307692,
        "Észak-Magyarország": 0.9024390244,
        "Dél-Alföld": 0.9692307692,
        "Észak-Alföld": 0.9,
        "Dél-Dunántúl": 0.75,
        "Szálláshely szolgálatatás, vendéglátás": 1.4324324324,
        "Építőipar": 0.9519230769,
        "Pénzügyi, biztosítási tevékenység": 1.1538461538,
        "Adminisztratív és szolgáltatást támogató tevékenység": 1.027027027,
        "Kereskedelem, gépjárműjavítás": 1.1052631579,
        "Ingatlanügyek": 1.6666666667,
        "Feldolgozóipar": 1.2857142857,
        "Információ, kommunikáció": 2.3333333333,
        "Egyéb (közigazgatás, oktatás, egészségügy, szociális ellátás, művészet, egyéb szolgáltatás)": 1.3305785124,
        "Szakmai, tudományos, műszaki tevékenység, könyvelés": 0.8666666667,
        "Villamosenergia-, gáz-, gőzellátás, légkondicionálás, vízellátás": 1.0,
        "Szállítás\/raktározás": 0.75,
        "Mezőgazdaság, bányászat": 0.6956521739,
        "5-9 fő": 0.9373040752,
        "20-49 fő": 1.3720930233,
        "10-19 fő": 1.335443038,
        "50-249 fő": 1.5641025641,
        "Informatikai eszközt használó munkavállalók": null
    },
    {
        "id": "B7b",
        "max_point": 3.0,
        "average_points": 0.0996677741,
        "Budapest": 0.1052631579,
        "Közép-Dunántúl": 0.037037037,
        "Pest megye": 0.1512605042,
        "Nyugat-Dunántúl": 0.1538461538,
        "Észak-Magyarország": 0.0487804878,
        "Dél-Alföld": 0.0769230769,
        "Észak-Alföld": 0.0833333333,
        "Dél-Dunántúl": 0.05,
        "Szálláshely szolgálatatás, vendéglátás": 0.0540540541,
        "Építőipar": 0.0480769231,
        "Pénzügyi, biztosítási tevékenység": 0.0,
        "Adminisztratív és szolgáltatást támogató tevékenység": 0.0,
        "Kereskedelem, gépjárműjavítás": 0.1776315789,
        "Ingatlanügyek": 0.0,
        "Feldolgozóipar": 0.1428571429,
        "Információ, kommunikáció": 0.0,
        "Egyéb (közigazgatás, oktatás, egészségügy, szociális ellátás, művészet, egyéb szolgáltatás)": 0.0991735537,
        "Szakmai, tudományos, műszaki tevékenység, könyvelés": 0.0,
        "Villamosenergia-, gáz-, gőzellátás, légkondicionálás, vízellátás": 0.2222222222,
        "Szállítás\/raktározás": 0.1875,
        "Mezőgazdaság, bányászat": 0.0,
        "5-9 fő": 0.0626959248,
        "20-49 fő": 0.1162790698,
        "10-19 fő": 0.1455696203,
        "50-249 fő": 0.1794871795,
        "Informatikai eszközt használó munkavállalók": null
    },
    {
        "id": "B8",
        "max_point": 3.0,
        "average_points": 1.4048780488,
        "Budapest": 1.2063492063,
        "Közép-Dunántúl": 1.6666666667,
        "Pest megye": 1.4761904762,
        "Nyugat-Dunántúl": 1.25,
        "Észak-Magyarország": 0.9523809524,
        "Dél-Alföld": 1.8421052632,
        "Észak-Alföld": 2.0833333333,
        "Dél-Dunántúl": 1.4285714286,
        "Szálláshely szolgálatatás, vendéglátás": 2.0,
        "Építőipar": 1.1923076923,
        "Pénzügyi, biztosítási tevékenység": 0.5,
        "Adminisztratív és szolgáltatást támogató tevékenység": 1.4615384615,
        "Kereskedelem, gépjárműjavítás": 1.4827586207,
        "Ingatlanügyek": 1.5,
        "Feldolgozóipar": 1.2173913043,
        "Információ, kommunikáció": 2.0,
        "Egyéb (közigazgatás, oktatás, egészségügy, szociális ellátás, művészet, egyéb szolgáltatás)": 1.3953488372,
        "Szakmai, tudományos, műszaki tevékenység, könyvelés": 0.0,
        "Villamosenergia-, gáz-, gőzellátás, légkondicionálás, vízellátás": 2.0,
        "Szállítás\/raktározás": 0.5,
        "Mezőgazdaság, bányászat": 1.4,
        "5-9 fő": 1.4019607843,
        "20-49 fő": 1.6923076923,
        "10-19 fő": 1.2537313433,
        "50-249 fő": 1.7,
        "Informatikai eszközt használó munkavállalók": null
    },
    {
        "id": "B9",
        "max_point": 2.0,
        "average_points": 1.843902439,
        "Budapest": 1.8095238095,
        "Közép-Dunántúl": 1.5555555556,
        "Pest megye": 2.0,
        "Nyugat-Dunántúl": 1.75,
        "Észak-Magyarország": 1.8095238095,
        "Dél-Alföld": 2.0,
        "Észak-Alföld": 1.8333333333,
        "Dél-Dunántúl": 1.8571428571,
        "Szálláshely szolgálatatás, vendéglátás": 2.0,
        "Építőipar": 1.7692307692,
        "Pénzügyi, biztosítási tevékenység": 2.0,
        "Adminisztratív és szolgáltatást támogató tevékenység": 1.8461538462,
        "Kereskedelem, gépjárműjavítás": 1.8275862069,
        "Ingatlanügyek": 2.0,
        "Feldolgozóipar": 1.8260869565,
        "Információ, kommunikáció": 2.0,
        "Egyéb (közigazgatás, oktatás, egészségügy, szociális ellátás, művészet, egyéb szolgáltatás)": 1.8139534884,
        "Szakmai, tudományos, műszaki tevékenység, könyvelés": 2.0,
        "Villamosenergia-, gáz-, gőzellátás, légkondicionálás, vízellátás": 2.0,
        "Szállítás\/raktározás": 2.0,
        "Mezőgazdaság, bányászat": 1.6,
        "5-9 fő": 1.8235294118,
        "20-49 fő": 1.9230769231,
        "10-19 fő": 1.8208955224,
        "50-249 fő": 2.0,
        "Informatikai eszközt használó munkavállalók": null
    },
    {
        "id": "C1",
        "max_point": 9.0,
        "average_points": 5.9950166113,
        "Budapest": 6.8596491228,
        "Közép-Dunántúl": 5.3518518519,
        "Pest megye": 6.1008403361,
        "Nyugat-Dunántúl": 6.3076923077,
        "Észak-Magyarország": 5.4390243902,
        "Dél-Alföld": 5.5230769231,
        "Észak-Alföld": 5.4666666667,
        "Dél-Dunántúl": 4.575,
        "Szálláshely szolgálatatás, vendéglátás": 4.8648648649,
        "Építőipar": 5.5096153846,
        "Pénzügyi, biztosítási tevékenység": 8.0,
        "Adminisztratív és szolgáltatást támogató tevékenység": 5.8378378378,
        "Kereskedelem, gépjárműjavítás": 5.9013157895,
        "Ingatlanügyek": 7.3333333333,
        "Feldolgozóipar": 5.7936507937,
        "Információ, kommunikáció": 9.0,
        "Egyéb (közigazgatás, oktatás, egészségügy, szociális ellátás, művészet, egyéb szolgáltatás)": 6.8347107438,
        "Szakmai, tudományos, műszaki tevékenység, könyvelés": 7.1333333333,
        "Villamosenergia-, gáz-, gőzellátás, légkondicionálás, vízellátás": 4.8888888889,
        "Szállítás\/raktározás": 4.9375,
        "Mezőgazdaság, bányászat": 5.1739130435,
        "5-9 fő": 5.6520376176,
        "20-49 fő": 6.3720930233,
        "10-19 fő": 6.1329113924,
        "50-249 fő": 7.4102564103,
        "Informatikai eszközt használó munkavállalók": null
    },
    {
        "id": "C2",
        "max_point": 10.0,
        "average_points": 3.7375415282,
        "Budapest": 5.350877193,
        "Közép-Dunántúl": 2.2222222222,
        "Pest megye": 3.4453781513,
        "Nyugat-Dunántúl": 4.2307692308,
        "Észak-Magyarország": 1.7073170732,
        "Dél-Alföld": 3.4615384615,
        "Észak-Alföld": 2.9166666667,
        "Dél-Dunántúl": 2.875,
        "Szálláshely szolgálatatás, vendéglátás": 3.2432432432,
        "Építőipar": 2.6442307692,
        "Pénzügyi, biztosítási tevékenység": 5.3846153846,
        "Adminisztratív és szolgáltatást támogató tevékenység": 6.0810810811,
        "Kereskedelem, gépjárműjavítás": 4.1776315789,
        "Ingatlanügyek": 3.3333333333,
        "Feldolgozóipar": 2.9365079365,
        "Információ, kommunikáció": 10.0,
        "Egyéb (közigazgatás, oktatás, egészségügy, szociális ellátás, művészet, egyéb szolgáltatás)": 4.0909090909,
        "Szakmai, tudományos, műszaki tevékenység, könyvelés": 2.3333333333,
        "Villamosenergia-, gáz-, gőzellátás, légkondicionálás, vízellátás": 3.3333333333,
        "Szállítás\/raktározás": 2.5,
        "Mezőgazdaság, bányászat": 2.6086956522,
        "5-9 fő": 2.6959247649,
        "20-49 fő": 5.0,
        "10-19 fő": 4.0506329114,
        "50-249 fő": 8.2051282051,
        "Informatikai eszközt használó munkavállalók": null
    },
    {
        "id": "C3",
        "max_point": 15.0,
        "average_points": 8.6362126246,
        "Budapest": 11.0350877193,
        "Közép-Dunántúl": 5.1296296296,
        "Pest megye": 9.0,
        "Nyugat-Dunántúl": 10.0576923077,
        "Észak-Magyarország": 6.1219512195,
        "Dél-Alföld": 6.7846153846,
        "Észak-Alföld": 7.7,
        "Dél-Dunántúl": 7.175,
        "Szálláshely szolgálatatás, vendéglátás": 5.7027027027,
        "Építőipar": 7.4903846154,
        "Pénzügyi, biztosítási tevékenység": 11.6153846154,
        "Adminisztratív és szolgáltatást támogató tevékenység": 10.4054054054,
        "Kereskedelem, gépjárműjavítás": 8.3223684211,
        "Ingatlanügyek": 7.5,
        "Feldolgozóipar": 8.9841269841,
        "Információ, kommunikáció": 13.1666666667,
        "Egyéb (közigazgatás, oktatás, egészségügy, szociális ellátás, művészet, egyéb szolgáltatás)": 9.9256198347,
        "Szakmai, tudományos, műszaki tevékenység, könyvelés": 11.8,
        "Villamosenergia-, gáz-, gőzellátás, légkondicionálás, vízellátás": 8.2222222222,
        "Szállítás\/raktározás": 8.9375,
        "Mezőgazdaság, bányászat": 5.347826087,
        "5-9 fő": 7.2695924765,
        "20-49 fő": 10.6395348837,
        "10-19 fő": 9.2848101266,
        "50-249 fő": 12.7692307692,
        "Informatikai eszközt használó munkavállalók": null
    },
    {
        "id": "C4",
        "max_point": 10.0,
        "average_points": 3.1597222222,
        "Budapest": 3.7125748503,
        "Közép-Dunántúl": 2.8,
        "Pest megye": 3.4513274336,
        "Nyugat-Dunántúl": 3.4615384615,
        "Észak-Magyarország": 2.6829268293,
        "Dél-Alföld": 2.6666666667,
        "Észak-Alföld": 2.6785714286,
        "Dél-Dunántúl": 1.8918918919,
        "Szálláshely szolgálatatás, vendéglátás": 1.5625,
        "Építőipar": 2.2916666667,
        "Pénzügyi, biztosítási tevékenység": 4.6153846154,
        "Adminisztratív és szolgáltatást támogató tevékenység": 5.7142857143,
        "Kereskedelem, gépjárműjavítás": 3.2450331126,
        "Ingatlanügyek": 3.3333333333,
        "Feldolgozóipar": 2.5423728814,
        "Információ, kommunikáció": 5.0,
        "Egyéb (közigazgatás, oktatás, egészségügy, szociális ellátás, művészet, egyéb szolgáltatás)": 3.4453781513,
        "Szakmai, tudományos, műszaki tevékenység, könyvelés": 4.0,
        "Villamosenergia-, gáz-, gőzellátás, légkondicionálás, vízellátás": 2.2222222222,
        "Szállítás\/raktározás": 3.3333333333,
        "Mezőgazdaság, bányászat": 3.0,
        "5-9 fő": 2.861952862,
        "20-49 fő": 3.9759036145,
        "10-19 fő": 2.8662420382,
        "50-249 fő": 4.8717948718,
        "Informatikai eszközt használó munkavállalók": null
    },
    {
        "id": "D1",
        "max_point": null,
        "average_points": null,
        "Budapest": null,
        "Közép-Dunántúl": null,
        "Pest megye": null,
        "Nyugat-Dunántúl": null,
        "Észak-Magyarország": null,
        "Dél-Alföld": null,
        "Észak-Alföld": null,
        "Dél-Dunántúl": null,
        "Szálláshely szolgálatatás, vendéglátás": null,
        "Építőipar": null,
        "Pénzügyi, biztosítási tevékenység": null,
        "Adminisztratív és szolgáltatást támogató tevékenység": null,
        "Kereskedelem, gépjárműjavítás": null,
        "Ingatlanügyek": null,
        "Feldolgozóipar": null,
        "Információ, kommunikáció": null,
        "Egyéb (közigazgatás, oktatás, egészségügy, szociális ellátás, művészet, egyéb szolgáltatás)": null,
        "Szakmai, tudományos, műszaki tevékenység, könyvelés": null,
        "Villamosenergia-, gáz-, gőzellátás, légkondicionálás, vízellátás": null,
        "Szállítás\/raktározás": null,
        "Mezőgazdaság, bányászat": null,
        "5-9 fő": null,
        "20-49 fő": null,
        "10-19 fő": null,
        "50-249 fő": null,
        "Informatikai eszközt használó munkavállalók": null
    },
    {
        "id": "D10",
        "max_point": null,
        "average_points": 25.4324324324,
        "Budapest": 22.1304347826,
        "Közép-Dunántúl": 30.0,
        "Pest megye": 20.35,
        "Nyugat-Dunántúl": 25.75,
        "Észak-Magyarország": 15.3333333333,
        "Dél-Alföld": 19.4285714286,
        "Észak-Alföld": 43.1,
        "Dél-Dunántúl": 40.0,
        "Szálláshely szolgálatatás, vendéglátás": 30.1428571429,
        "Építőipar": 11.2,
        "Pénzügyi, biztosítási tevékenység": null,
        "Adminisztratív és szolgáltatást támogató tevékenység": 11.0,
        "Kereskedelem, gépjárműjavítás": 22.5641025641,
        "Ingatlanügyek": null,
        "Feldolgozóipar": 31.2222222222,
        "Információ, kommunikáció": 100.0,
        "Egyéb (közigazgatás, oktatás, egészségügy, szociális ellátás, művészet, egyéb szolgáltatás)": 46.2,
        "Szakmai, tudományos, műszaki tevékenység, könyvelés": 20.0,
        "Villamosenergia-, gáz-, gőzellátás, légkondicionálás, vízellátás": 1.0,
        "Szállítás\/raktározás": 10.0,
        "Mezőgazdaság, bányászat": 23.3333333333,
        "5-9 fő": 29.0294117647,
        "20-49 fő": 22.0,
        "10-19 fő": 23.9444444444,
        "50-249 fő": 19.5,
        "Informatikai eszközt használó munkavállalók": null
    },
    {
        "id": "D2",
        "max_point": null,
        "average_points": 40742.1926910299,
        "Budapest": 24698.3391812865,
        "Közép-Dunántúl": 25088.5740740741,
        "Pest megye": 17891.218487395,
        "Nyugat-Dunántúl": 37129.3076923077,
        "Észak-Magyarország": 93108.9024390244,
        "Dél-Alföld": 77646.5846153846,
        "Észak-Alföld": 87988.9166666667,
        "Dél-Dunántúl": 18624.85,
        "Szálláshely szolgálatatás, vendéglátás": 48581.5945945946,
        "Építőipar": 185.9807692308,
        "Pénzügyi, biztosítási tevékenység": 259.0769230769,
        "Adminisztratív és szolgáltatást támogató tevékenység": 127346.1621621622,
        "Kereskedelem, gépjárműjavítás": 78752.4539473684,
        "Ingatlanügyek": 1221.1666666667,
        "Feldolgozóipar": 8306.7301587302,
        "Információ, kommunikáció": 56.5,
        "Egyéb (közigazgatás, oktatás, egészségügy, szociális ellátás, művészet, egyéb szolgáltatás)": 44958.5950413223,
        "Szakmai, tudományos, műszaki tevékenység, könyvelés": 134.5333333333,
        "Villamosenergia-, gáz-, gőzellátás, légkondicionálás, vízellátás": 720.5555555556,
        "Szállítás\/raktározás": 2278.5625,
        "Mezőgazdaság, bányászat": 367.3913043478,
        "5-9 fő": 28295.1943573668,
        "20-49 fő": 133678.1976744186,
        "10-19 fő": 18598.5759493671,
        "50-249 fő": 27326.4871794872,
        "Informatikai eszközt használó munkavállalók": null
    },
    {
        "id": "D3",
        "max_point": null,
        "average_points": null,
        "Budapest": null,
        "Közép-Dunántúl": null,
        "Pest megye": null,
        "Nyugat-Dunántúl": null,
        "Észak-Magyarország": null,
        "Dél-Alföld": null,
        "Észak-Alföld": null,
        "Dél-Dunántúl": null,
        "Szálláshely szolgálatatás, vendéglátás": null,
        "Építőipar": null,
        "Pénzügyi, biztosítási tevékenység": null,
        "Adminisztratív és szolgáltatást támogató tevékenység": null,
        "Kereskedelem, gépjárműjavítás": null,
        "Ingatlanügyek": null,
        "Feldolgozóipar": null,
        "Információ, kommunikáció": null,
        "Egyéb (közigazgatás, oktatás, egészségügy, szociális ellátás, művészet, egyéb szolgáltatás)": null,
        "Szakmai, tudományos, műszaki tevékenység, könyvelés": null,
        "Villamosenergia-, gáz-, gőzellátás, légkondicionálás, vízellátás": null,
        "Szállítás\/raktározás": null,
        "Mezőgazdaság, bányászat": null,
        "5-9 fő": null,
        "20-49 fő": null,
        "10-19 fő": null,
        "50-249 fő": null,
        "Informatikai eszközt használó munkavállalók": null
    },
    {
        "id": "D4",
        "max_point": null,
        "average_points": null,
        "Budapest": null,
        "Közép-Dunántúl": null,
        "Pest megye": null,
        "Nyugat-Dunántúl": null,
        "Észak-Magyarország": null,
        "Dél-Alföld": null,
        "Észak-Alföld": null,
        "Dél-Dunántúl": null,
        "Szálláshely szolgálatatás, vendéglátás": null,
        "Építőipar": null,
        "Pénzügyi, biztosítási tevékenység": null,
        "Adminisztratív és szolgáltatást támogató tevékenység": null,
        "Kereskedelem, gépjárműjavítás": null,
        "Ingatlanügyek": null,
        "Feldolgozóipar": null,
        "Információ, kommunikáció": null,
        "Egyéb (közigazgatás, oktatás, egészségügy, szociális ellátás, művészet, egyéb szolgáltatás)": null,
        "Szakmai, tudományos, műszaki tevékenység, könyvelés": null,
        "Villamosenergia-, gáz-, gőzellátás, légkondicionálás, vízellátás": null,
        "Szállítás\/raktározás": null,
        "Mezőgazdaság, bányászat": null,
        "5-9 fő": null,
        "20-49 fő": null,
        "10-19 fő": null,
        "50-249 fő": null,
        "Informatikai eszközt használó munkavállalók": null
    },
    {
        "id": "D5",
        "max_point": 35.0,
        "average_points": 12.2568093385,
        "Budapest": 13.4,
        "Közép-Dunántúl": 11.25,
        "Pest megye": 13.8235294118,
        "Nyugat-Dunántúl": 10.0,
        "Észak-Magyarország": 8.8235294118,
        "Dél-Alföld": 12.4074074074,
        "Észak-Alföld": 9.8214285714,
        "Dél-Dunántúl": 13.6111111111,
        "Szálláshely szolgálatatás, vendéglátás": 16.4285714286,
        "Építőipar": 12.3333333333,
        "Pénzügyi, biztosítási tevékenység": 0.0,
        "Adminisztratív és szolgáltatást támogató tevékenység": 12.8947368421,
        "Kereskedelem, gépjárműjavítás": 9.9350649351,
        "Ingatlanügyek": 13.3333333333,
        "Feldolgozóipar": 11.5384615385,
        "Információ, kommunikáció": 17.5,
        "Egyéb (közigazgatás, oktatás, egészségügy, szociális ellátás, művészet, egyéb szolgáltatás)": 13.7962962963,
        "Szakmai, tudományos, műszaki tevékenység, könyvelés": 10.0,
        "Villamosenergia-, gáz-, gőzellátás, légkondicionálás, vízellátás": 10.0,
        "Szállítás\/raktározás": 16.25,
        "Mezőgazdaság, bányászat": 14.0909090909,
        "5-9 fő": 11.4622641509,
        "20-49 fő": 13.2978723404,
        "10-19 fő": 12.4691358025,
        "50-249 fő": 13.0434782609,
        "Informatikai eszközt használó munkavállalók": null
    },
    {
        "id": "D6",
        "max_point": 40.0,
        "average_points": 5.1827242525,
        "Budapest": 6.6081871345,
        "Közép-Dunántúl": 3.5185185185,
        "Pest megye": 4.9159663866,
        "Nyugat-Dunántúl": 4.8076923077,
        "Észak-Magyarország": 4.0243902439,
        "Dél-Alföld": 4.1538461538,
        "Észak-Alföld": 4.9166666667,
        "Dél-Dunántúl": 5.875,
        "Szálláshely szolgálatatás, vendéglátás": 5.2702702703,
        "Építőipar": 3.6538461538,
        "Pénzügyi, biztosítási tevékenység": 4.2307692308,
        "Adminisztratív és szolgáltatást támogató tevékenység": 5.9459459459,
        "Kereskedelem, gépjárműjavítás": 6.8421052632,
        "Ingatlanügyek": 3.3333333333,
        "Feldolgozóipar": 3.4126984127,
        "Információ, kommunikáció": 14.1666666667,
        "Egyéb (közigazgatás, oktatás, egészségügy, szociális ellátás, művészet, egyéb szolgáltatás)": 5.7438016529,
        "Szakmai, tudományos, műszaki tevékenység, könyvelés": 0.0,
        "Villamosenergia-, gáz-, gőzellátás, légkondicionálás, vízellátás": 6.1111111111,
        "Szállítás\/raktározás": 1.5625,
        "Mezőgazdaság, bányászat": 5.8695652174,
        "5-9 fő": 3.9655172414,
        "20-49 fő": 8.1395348837,
        "10-19 fő": 5.6962025316,
        "50-249 fő": 6.5384615385,
        "Informatikai eszközt használó munkavállalók": null
    },
    {
        "id": "D7",
        "max_point": 51.0,
        "average_points": 9.7225913621,
        "Budapest": 10.0175438596,
        "Közép-Dunántúl": 6.8888888889,
        "Pest megye": 12.2268907563,
        "Nyugat-Dunántúl": 9.2884615385,
        "Észak-Magyarország": 7.4634146341,
        "Dél-Alföld": 6.3230769231,
        "Észak-Alföld": 11.85,
        "Dél-Dunántúl": 10.05,
        "Szálláshely szolgálatatás, vendéglátás": 15.1621621622,
        "Építőipar": 7.6730769231,
        "Pénzügyi, biztosítási tevékenység": 6.0,
        "Adminisztratív és szolgáltatást támogató tevékenység": 5.7567567568,
        "Kereskedelem, gépjárműjavítás": 13.1842105263,
        "Ingatlanügyek": 4.5,
        "Feldolgozóipar": 10.4285714286,
        "Információ, kommunikáció": 9.0,
        "Egyéb (közigazgatás, oktatás, egészségügy, szociális ellátás, művészet, egyéb szolgáltatás)": 7.3140495868,
        "Szakmai, tudományos, műszaki tevékenység, könyvelés": 7.2,
        "Villamosenergia-, gáz-, gőzellátás, légkondicionálás, vízellátás": 13.3333333333,
        "Szállítás\/raktározás": 8.4375,
        "Mezőgazdaság, bányászat": 9.2608695652,
        "5-9 fő": 8.8495297806,
        "20-49 fő": 11.511627907,
        "10-19 fő": 10.1012658228,
        "50-249 fő": 11.3846153846,
        "Informatikai eszközt használó munkavállalók": null
    },
    {
        "id": "D8",
        "max_point": 15.0,
        "average_points": 0.4302325581,
        "Budapest": 0.7543859649,
        "Közép-Dunántúl": 0.0740740741,
        "Pest megye": 0.268907563,
        "Nyugat-Dunántúl": 0.0769230769,
        "Észak-Magyarország": 0.6585365854,
        "Dél-Alföld": 0.4307692308,
        "Észak-Alföld": 0.3166666667,
        "Dél-Dunántúl": 0.4,
        "Szálláshely szolgálatatás, vendéglátás": 0.4324324324,
        "Építőipar": 0.1730769231,
        "Pénzügyi, biztosítási tevékenység": 0.3846153846,
        "Adminisztratív és szolgáltatást támogató tevékenység": 0.0810810811,
        "Kereskedelem, gépjárműjavítás": 0.5526315789,
        "Ingatlanügyek": 0.1666666667,
        "Feldolgozóipar": 0.5079365079,
        "Információ, kommunikáció": 3.0,
        "Egyéb (közigazgatás, oktatás, egészségügy, szociális ellátás, művészet, egyéb szolgáltatás)": 0.5619834711,
        "Szakmai, tudományos, műszaki tevékenység, könyvelés": 0.0666666667,
        "Villamosenergia-, gáz-, gőzellátás, légkondicionálás, vízellátás": 0.8888888889,
        "Szállítás\/raktározás": 0.3125,
        "Mezőgazdaság, bányászat": 0.0,
        "5-9 fő": 0.3166144201,
        "20-49 fő": 0.2209302326,
        "10-19 fő": 0.6265822785,
        "50-249 fő": 1.0256410256,
        "Informatikai eszközt használó munkavállalók": null
    },
    {
        "id": "D9",
        "max_point": 23.0,
        "average_points": 2.1727574751,
        "Budapest": 2.6315789474,
        "Közép-Dunántúl": 0.2592592593,
        "Pest megye": 2.8991596639,
        "Nyugat-Dunántúl": 1.4615384615,
        "Észak-Magyarország": 1.512195122,
        "Dél-Alföld": 1.5230769231,
        "Észak-Alföld": 2.6833333333,
        "Dél-Dunántúl": 2.525,
        "Szálláshely szolgálatatás, vendéglátás": 2.5405405405,
        "Építőipar": 0.5769230769,
        "Pénzügyi, biztosítási tevékenység": 0.0,
        "Adminisztratív és szolgáltatást támogató tevékenység": 1.2432432432,
        "Kereskedelem, gépjárműjavítás": 5.1710526316,
        "Ingatlanügyek": 0.0,
        "Feldolgozóipar": 1.9365079365,
        "Információ, kommunikáció": 1.1666666667,
        "Egyéb (közigazgatás, oktatás, egészségügy, szociális ellátás, művészet, egyéb szolgáltatás)": 0.3801652893,
        "Szakmai, tudományos, műszaki tevékenység, könyvelés": 2.1333333333,
        "Villamosenergia-, gáz-, gőzellátás, légkondicionálás, vízellátás": 0.7777777778,
        "Szállítás\/raktározás": 2.4375,
        "Mezőgazdaság, bányászat": 3.0,
        "5-9 fő": 1.8244514107,
        "20-49 fő": 3.0,
        "10-19 fő": 2.1202531646,
        "50-249 fő": 3.4102564103,
        "Informatikai eszközt használó munkavállalók": null
    },
    {
        "id": "E1",
        "max_point": 16.0,
        "average_points": 4.4551495017,
        "Budapest": 5.0584795322,
        "Közép-Dunántúl": 3.4814814815,
        "Pest megye": 4.7142857143,
        "Nyugat-Dunántúl": 4.9807692308,
        "Észak-Magyarország": 3.9512195122,
        "Dél-Alföld": 3.6307692308,
        "Észak-Alföld": 3.8166666667,
        "Dél-Dunántúl": 4.55,
        "Szálláshely szolgálatatás, vendéglátás": 3.7027027027,
        "Építőipar": 4.3942307692,
        "Pénzügyi, biztosítási tevékenység": 5.1538461538,
        "Adminisztratív és szolgáltatást támogató tevékenység": 4.5135135135,
        "Kereskedelem, gépjárműjavítás": 4.4473684211,
        "Ingatlanügyek": 5.6666666667,
        "Feldolgozóipar": 4.2857142857,
        "Információ, kommunikáció": 6.8333333333,
        "Egyéb (közigazgatás, oktatás, egészségügy, szociális ellátás, művészet, egyéb szolgáltatás)": 4.6280991736,
        "Szakmai, tudományos, műszaki tevékenység, könyvelés": 6.0666666667,
        "Villamosenergia-, gáz-, gőzellátás, légkondicionálás, vízellátás": 4.8888888889,
        "Szállítás\/raktározás": 3.875,
        "Mezőgazdaság, bányászat": 3.3043478261,
        "5-9 fő": 4.0940438871,
        "20-49 fő": 4.7558139535,
        "10-19 fő": 4.8544303797,
        "50-249 fő": 5.1282051282,
        "Informatikai eszközt használó munkavállalók": null
    },
    {
        "id": "E2",
        "max_point": 15.0,
        "average_points": 11.342192691,
        "Budapest": 11.6666666667,
        "Közép-Dunántúl": 10.5,
        "Pest megye": 11.1008403361,
        "Nyugat-Dunántúl": 12.3461538462,
        "Észak-Magyarország": 11.4634146341,
        "Dél-Alföld": 10.1846153846,
        "Észak-Alföld": 11.7333333333,
        "Dél-Dunántúl": 11.675,
        "Szálláshely szolgálatatás, vendéglátás": 10.6756756757,
        "Építőipar": 11.3076923077,
        "Pénzügyi, biztosítási tevékenység": 12.1538461538,
        "Adminisztratív és szolgáltatást támogató tevékenység": 12.8648648649,
        "Kereskedelem, gépjárműjavítás": 10.7894736842,
        "Ingatlanügyek": 12.5,
        "Feldolgozóipar": 11.2222222222,
        "Információ, kommunikáció": 11.3333333333,
        "Egyéb (közigazgatás, oktatás, egészségügy, szociális ellátás, művészet, egyéb szolgáltatás)": 11.8595041322,
        "Szakmai, tudományos, műszaki tevékenység, könyvelés": 11.6666666667,
        "Villamosenergia-, gáz-, gőzellátás, légkondicionálás, vízellátás": 11.7777777778,
        "Szállítás\/raktározás": 9.5625,
        "Mezőgazdaság, bányászat": 11.4782608696,
        "5-9 fő": 10.8902821317,
        "20-49 fő": 11.9418604651,
        "10-19 fő": 11.4367088608,
        "50-249 fő": 13.3333333333,
        "Informatikai eszközt használó munkavállalók": null
    },
    {
        "id": "E3",
        "max_point": 15.0,
        "average_points": 9.4468438538,
        "Budapest": 11.1052631579,
        "Közép-Dunántúl": 6.5185185185,
        "Pest megye": 9.0504201681,
        "Nyugat-Dunántúl": 9.9230769231,
        "Észak-Magyarország": 8.243902439,
        "Dél-Alföld": 8.2615384615,
        "Észak-Alföld": 10.2666666667,
        "Dél-Dunántúl": 8.8,
        "Szálláshely szolgálatatás, vendéglátás": 7.7027027027,
        "Építőipar": 8.0288461538,
        "Pénzügyi, biztosítási tevékenység": 13.6153846154,
        "Adminisztratív és szolgáltatást támogató tevékenység": 12.2972972973,
        "Kereskedelem, gépjárműjavítás": 9.8223684211,
        "Ingatlanügyek": 11.8333333333,
        "Feldolgozóipar": 8.5238095238,
        "Információ, kommunikáció": 11.8333333333,
        "Egyéb (közigazgatás, oktatás, egészségügy, szociális ellátás, művészet, egyéb szolgáltatás)": 10.0165289256,
        "Szakmai, tudományos, műszaki tevékenység, könyvelés": 7.8,
        "Villamosenergia-, gáz-, gőzellátás, légkondicionálás, vízellátás": 10.0,
        "Szállítás\/raktározás": 9.5625,
        "Mezőgazdaság, bányászat": 8.3043478261,
        "5-9 fő": 8.6018808777,
        "20-49 fő": 10.1860465116,
        "10-19 fő": 10.1202531646,
        "50-249 fő": 12.0,
        "Informatikai eszközt használó munkavállalók": null
    },
    {
        "id": "E4",
        "max_point": null,
        "average_points": null,
        "Budapest": null,
        "Közép-Dunántúl": null,
        "Pest megye": null,
        "Nyugat-Dunántúl": null,
        "Észak-Magyarország": null,
        "Dél-Alföld": null,
        "Észak-Alföld": null,
        "Dél-Dunántúl": null,
        "Szálláshely szolgálatatás, vendéglátás": null,
        "Építőipar": null,
        "Pénzügyi, biztosítási tevékenység": null,
        "Adminisztratív és szolgáltatást támogató tevékenység": null,
        "Kereskedelem, gépjárműjavítás": null,
        "Ingatlanügyek": null,
        "Feldolgozóipar": null,
        "Információ, kommunikáció": null,
        "Egyéb (közigazgatás, oktatás, egészségügy, szociális ellátás, művészet, egyéb szolgáltatás)": null,
        "Szakmai, tudományos, műszaki tevékenység, könyvelés": null,
        "Villamosenergia-, gáz-, gőzellátás, légkondicionálás, vízellátás": null,
        "Szállítás\/raktározás": null,
        "Mezőgazdaság, bányászat": null,
        "5-9 fő": null,
        "20-49 fő": null,
        "10-19 fő": null,
        "50-249 fő": null,
        "Informatikai eszközt használó munkavállalók": null
    },
    {
        "id": "E5",
        "max_point": 4.0,
        "average_points": 1.4451827243,
        "Budapest": 1.6257309942,
        "Közép-Dunántúl": 1.037037037,
        "Pest megye": 1.5462184874,
        "Nyugat-Dunántúl": 1.8461538462,
        "Észak-Magyarország": 1.1219512195,
        "Dél-Alföld": 1.1076923077,
        "Észak-Alföld": 1.3666666667,
        "Dél-Dunántúl": 1.4,
        "Szálláshely szolgálatatás, vendéglátás": 1.7837837838,
        "Építőipar": 1.0384615385,
        "Pénzügyi, biztosítási tevékenység": 1.3846153846,
        "Adminisztratív és szolgáltatást támogató tevékenység": 1.8918918919,
        "Kereskedelem, gépjárműjavítás": 1.4342105263,
        "Ingatlanügyek": 1.6666666667,
        "Feldolgozóipar": 1.5873015873,
        "Információ, kommunikáció": 2.3333333333,
        "Egyéb (közigazgatás, oktatás, egészségügy, szociális ellátás, művészet, egyéb szolgáltatás)": 1.4545454545,
        "Szakmai, tudományos, műszaki tevékenység, könyvelés": 1.6,
        "Villamosenergia-, gáz-, gőzellátás, légkondicionálás, vízellátás": 1.3333333333,
        "Szállítás\/raktározás": 1.625,
        "Mezőgazdaság, bányászat": 1.2173913043,
        "5-9 fő": 1.1285266458,
        "20-49 fő": 2.0,
        "10-19 fő": 1.582278481,
        "50-249 fő": 2.2564102564,
        "Informatikai eszközt használó munkavállalók": null
    },
    {
        "id": "F1",
        "max_point": 17.0,
        "average_points": 6.5520833333,
        "Budapest": 8.6526946108,
        "Közép-Dunántúl": 5.1,
        "Pest megye": 6.6194690265,
        "Nyugat-Dunántúl": 6.8653846154,
        "Észak-Magyarország": 4.1463414634,
        "Dél-Alföld": 5.6666666667,
        "Észak-Alföld": 4.5535714286,
        "Dél-Dunántúl": 5.5135135135,
        "Szálláshely szolgálatatás, vendéglátás": 6.90625,
        "Építőipar": 3.8958333333,
        "Pénzügyi, biztosítási tevékenység": 5.2307692308,
        "Adminisztratív és szolgáltatást támogató tevékenység": 8.2571428571,
        "Kereskedelem, gépjárműjavítás": 7.0927152318,
        "Ingatlanügyek": 11.3333333333,
        "Feldolgozóipar": 5.7627118644,
        "Információ, kommunikáció": 8.5,
        "Egyéb (közigazgatás, oktatás, egészségügy, szociális ellátás, művészet, egyéb szolgáltatás)": 8.0,
        "Szakmai, tudományos, műszaki tevékenység, könyvelés": 6.8,
        "Villamosenergia-, gáz-, gőzellátás, légkondicionálás, vízellátás": 7.5555555556,
        "Szállítás\/raktározás": 4.5333333333,
        "Mezőgazdaság, bányászat": 5.1,
        "5-9 fő": 4.8080808081,
        "20-49 fő": 7.9879518072,
        "10-19 fő": 7.4713375796,
        "50-249 fő": 13.0769230769,
        "Informatikai eszközt használó munkavállalók": null
    },
    {
        "id": "F2",
        "max_point": 27.0,
        "average_points": 11.7790697674,
        "Budapest": 14.1520467836,
        "Közép-Dunántúl": 7.0740740741,
        "Pest megye": 11.7058823529,
        "Nyugat-Dunántúl": 14.0384615385,
        "Észak-Magyarország": 11.0243902439,
        "Dél-Alföld": 11.3076923077,
        "Észak-Alföld": 9.6833333333,
        "Dél-Dunántúl": 9.95,
        "Szálláshely szolgálatatás, vendéglátás": 7.8108108108,
        "Építőipar": 10.2307692308,
        "Pénzügyi, biztosítási tevékenység": 16.0769230769,
        "Adminisztratív és szolgáltatást támogató tevékenység": 12.9189189189,
        "Kereskedelem, gépjárműjavítás": 11.4934210526,
        "Ingatlanügyek": 7.0,
        "Feldolgozóipar": 11.9682539683,
        "Információ, kommunikáció": 18.0,
        "Egyéb (közigazgatás, oktatás, egészségügy, szociális ellátás, művészet, egyéb szolgáltatás)": 14.6033057851,
        "Szakmai, tudományos, műszaki tevékenység, könyvelés": 13.4666666667,
        "Villamosenergia-, gáz-, gőzellátás, légkondicionálás, vízellátás": 12.3333333333,
        "Szállítás\/raktározás": 9.0,
        "Mezőgazdaság, bányászat": 7.652173913,
        "5-9 fő": 10.0971786834,
        "20-49 fő": 13.488372093,
        "10-19 fő": 13.664556962,
        "50-249 fő": 14.1282051282,
        "Informatikai eszközt használó munkavállalók": null
    },
    {
        "id": "F3_1",
        "max_point": 13.0,
        "average_points": 10.96875,
        "Budapest": 11.754491018,
        "Közép-Dunántúl": 10.14,
        "Pest megye": 10.814159292,
        "Nyugat-Dunántúl": 11.25,
        "Észak-Magyarország": 10.7804878049,
        "Dél-Alföld": 10.4,
        "Észak-Alföld": 10.9107142857,
        "Dél-Dunántúl": 9.8378378378,
        "Szálláshely szolgálatatás, vendéglátás": 10.5625,
        "Építőipar": 10.15625,
        "Pénzügyi, biztosítási tevékenység": 12.0,
        "Adminisztratív és szolgáltatást támogató tevékenység": 11.5142857143,
        "Kereskedelem, gépjárműjavítás": 11.1920529801,
        "Ingatlanügyek": 13.0,
        "Feldolgozóipar": 10.1355932203,
        "Információ, kommunikáció": 13.0,
        "Egyéb (közigazgatás, oktatás, egészségügy, szociális ellátás, művészet, egyéb szolgáltatás)": 11.2521008403,
        "Szakmai, tudományos, műszaki tevékenység, könyvelés": 9.5333333333,
        "Villamosenergia-, gáz-, gőzellátás, légkondicionálás, vízellátás": 10.1111111111,
        "Szállítás\/raktározás": 12.1333333333,
        "Mezőgazdaság, bányászat": 12.35,
        "5-9 fő": 10.1986531987,
        "20-49 fő": 11.9036144578,
        "10-19 fő": 11.5095541401,
        "50-249 fő": 12.6666666667,
        "Informatikai eszközt használó munkavállalók": null
    },
    {
        "id": "F3_2",
        "max_point": 12.0,
        "average_points": 9.306122449,
        "Budapest": 10.125,
        "Közép-Dunántúl": 8.5714285714,
        "Pest megye": 9.7215189873,
        "Nyugat-Dunántúl": 9.9428571429,
        "Észak-Magyarország": 8.7272727273,
        "Dél-Alföld": 7.5,
        "Észak-Alföld": 8.3076923077,
        "Dél-Dunántúl": 8.5714285714,
        "Szálláshely szolgálatatás, vendéglátás": 9.6,
        "Építőipar": 8.6,
        "Pénzügyi, biztosítási tevékenység": 12.0,
        "Adminisztratív és szolgáltatást támogató tevékenység": 9.7777777778,
        "Kereskedelem, gépjárműjavítás": 8.8484848485,
        "Ingatlanügyek": 4.0,
        "Feldolgozóipar": 9.5384615385,
        "Információ, kommunikáció": 7.2,
        "Egyéb (közigazgatás, oktatás, egészségügy, szociális ellátás, művészet, egyéb szolgáltatás)": 10.0235294118,
        "Szakmai, tudományos, műszaki tevékenység, könyvelés": 10.0,
        "Villamosenergia-, gáz-, gőzellátás, légkondicionálás, vízellátás": 9.0,
        "Szállítás\/raktározás": 9.0,
        "Mezőgazdaság, bányászat": 9.2307692308,
        "5-9 fő": 8.8556149733,
        "20-49 fő": 9.2459016393,
        "10-19 fő": 9.5789473684,
        "50-249 fő": 11.2,
        "Informatikai eszközt használó munkavállalók": null
    },
    {
        "id": "G1_2",
        "max_point": 16.0,
        "average_points": 9.8338870432,
        "Budapest": 9.918128655,
        "Közép-Dunántúl": 8.8888888889,
        "Pest megye": 11.2941176471,
        "Nyugat-Dunántúl": 10.1538461538,
        "Észak-Magyarország": 10.1463414634,
        "Dél-Alföld": 8.3692307692,
        "Észak-Alföld": 9.6,
        "Dél-Dunántúl": 8.4,
        "Szálláshely szolgálatatás, vendéglátás": 9.9459459459,
        "Építőipar": 10.7692307692,
        "Pénzügyi, biztosítási tevékenység": 11.0769230769,
        "Adminisztratív és szolgáltatást támogató tevékenység": 10.3783783784,
        "Kereskedelem, gépjárműjavítás": 8.3157894737,
        "Ingatlanügyek": 5.3333333333,
        "Feldolgozóipar": 11.9365079365,
        "Információ, kommunikáció": 13.3333333333,
        "Egyéb (közigazgatás, oktatás, egészségügy, szociális ellátás, művészet, egyéb szolgáltatás)": 9.1239669421,
        "Szakmai, tudományos, műszaki tevékenység, könyvelés": 14.9333333333,
        "Villamosenergia-, gáz-, gőzellátás, légkondicionálás, vízellátás": 14.2222222222,
        "Szállítás\/raktározás": 11.0,
        "Mezőgazdaság, bányászat": 6.2608695652,
        "5-9 fő": 9.9811912226,
        "20-49 fő": 9.488372093,
        "10-19 fő": 10.1265822785,
        "50-249 fő": 8.2051282051,
        "Informatikai eszközt használó munkavállalók": null
    },
    {
        "id": "G1_1",
        "max_point": 14.0,
        "average_points": 12.3023255814,
        "Budapest": 12.3625730994,
        "Közép-Dunántúl": 11.1481481481,
        "Pest megye": 12.5882352941,
        "Nyugat-Dunántúl": 12.6538461538,
        "Észak-Magyarország": 12.6341463415,
        "Dél-Alföld": 11.4153846154,
        "Észak-Alföld": 12.6,
        "Dél-Dunántúl": 12.95,
        "Szálláshely szolgálatatás, vendéglátás": 12.8648648649,
        "Építőipar": 12.5192307692,
        "Pénzügyi, biztosítási tevékenység": 12.9230769231,
        "Adminisztratív és szolgáltatást támogató tevékenység": 14.0,
        "Kereskedelem, gépjárműjavítás": 11.2368421053,
        "Ingatlanügyek": 11.6666666667,
        "Feldolgozóipar": 12.8888888889,
        "Információ, kommunikáció": 14.0,
        "Egyéb (közigazgatás, oktatás, egészségügy, szociális ellátás, művészet, egyéb szolgáltatás)": 12.0330578512,
        "Szakmai, tudományos, műszaki tevékenység, könyvelés": 13.0666666667,
        "Villamosenergia-, gáz-, gőzellátás, légkondicionálás, vízellátás": 14.0,
        "Szállítás\/raktározás": 12.25,
        "Mezőgazdaság, bányászat": 12.7826086957,
        "5-9 fő": 12.5517241379,
        "20-49 fő": 11.8837209302,
        "10-19 fő": 12.2278481013,
        "50-249 fő": 11.4871794872,
        "Informatikai eszközt használó munkavállalók": null
    },
    {
        "id": "G2",
        "max_point": 10.0,
        "average_points": 9.4684385382,
        "Budapest": 9.5906432749,
        "Közép-Dunántúl": 8.7037037037,
        "Pest megye": 9.4957983193,
        "Nyugat-Dunántúl": 10.0,
        "Észak-Magyarország": 10.0,
        "Dél-Alföld": 9.0769230769,
        "Észak-Alföld": 9.3333333333,
        "Dél-Dunántúl": 9.5,
        "Szálláshely szolgálatatás, vendéglátás": 9.7297297297,
        "Építőipar": 9.7115384615,
        "Pénzügyi, biztosítási tevékenység": 8.4615384615,
        "Adminisztratív és szolgáltatást támogató tevékenység": 9.4594594595,
        "Kereskedelem, gépjárműjavítás": 9.4736842105,
        "Ingatlanügyek": 6.6666666667,
        "Feldolgozóipar": 9.5238095238,
        "Információ, kommunikáció": 8.3333333333,
        "Egyéb (közigazgatás, oktatás, egészségügy, szociális ellátás, művészet, egyéb szolgáltatás)": 9.5041322314,
        "Szakmai, tudományos, műszaki tevékenység, könyvelés": 9.3333333333,
        "Villamosenergia-, gáz-, gőzellátás, légkondicionálás, vízellátás": 10.0,
        "Szállítás\/raktározás": 9.375,
        "Mezőgazdaság, bányászat": 9.1304347826,
        "5-9 fő": 9.5297805643,
        "20-49 fő": 9.5348837209,
        "10-19 fő": 9.6202531646,
        "50-249 fő": 8.2051282051,
        "Informatikai eszközt használó munkavállalók": null
    },
    {
        "id": "G3",
        "max_point": 10.0,
        "average_points": 6.7109634551,
        "Budapest": 7.2514619883,
        "Közép-Dunántúl": 6.1111111111,
        "Pest megye": 6.6386554622,
        "Nyugat-Dunántúl": 6.7307692308,
        "Észak-Magyarország": 6.5853658537,
        "Dél-Alföld": 6.0,
        "Észak-Alföld": 6.6666666667,
        "Dél-Dunántúl": 6.75,
        "Szálláshely szolgálatatás, vendéglátás": 8.1081081081,
        "Építőipar": 6.5384615385,
        "Pénzügyi, biztosítási tevékenység": 6.9230769231,
        "Adminisztratív és szolgáltatást támogató tevékenység": 6.2162162162,
        "Kereskedelem, gépjárműjavítás": 6.25,
        "Ingatlanügyek": 3.3333333333,
        "Feldolgozóipar": 7.619047619,
        "Információ, kommunikáció": 10.0,
        "Egyéb (közigazgatás, oktatás, egészségügy, szociális ellátás, művészet, egyéb szolgáltatás)": 6.9421487603,
        "Szakmai, tudományos, műszaki tevékenység, könyvelés": 6.6666666667,
        "Villamosenergia-, gáz-, gőzellátás, légkondicionálás, vízellátás": 8.8888888889,
        "Szállítás\/raktározás": 6.25,
        "Mezőgazdaság, bányászat": 4.7826086957,
        "5-9 fő": 6.5830721003,
        "20-49 fő": 6.976744186,
        "10-19 fő": 6.6455696203,
        "50-249 fő": 7.4358974359,
        "Informatikai eszközt használó munkavállalók": null
    },
    {
        "id": "G4",
        "max_point": null,
        "average_points": 59.7178217822,
        "Budapest": 66.9193548387,
        "Közép-Dunántúl": 58.6666666667,
        "Pest megye": 57.0253164557,
        "Nyugat-Dunántúl": 52.6571428571,
        "Észak-Magyarország": 47.6296296296,
        "Dél-Alföld": 55.8974358974,
        "Észak-Alföld": 58.425,
        "Dél-Dunántúl": 64.4814814815,
        "Szálláshely szolgálatatás, vendéglátás": 57.8666666667,
        "Építőipar": 72.3823529412,
        "Pénzügyi, biztosítási tevékenység": 61.1111111111,
        "Adminisztratív és szolgáltatást támogató tevékenység": 64.347826087,
        "Kereskedelem, gépjárműjavítás": 42.9368421053,
        "Ingatlanügyek": 65.0,
        "Feldolgozóipar": 60.9166666667,
        "Információ, kommunikáció": 83.1666666667,
        "Egyéb (közigazgatás, oktatás, egészségügy, szociális ellátás, művészet, egyéb szolgáltatás)": 64.4404761905,
        "Szakmai, tudományos, műszaki tevékenység, könyvelés": 52.3,
        "Villamosenergia-, gáz-, gőzellátás, légkondicionálás, vízellátás": 68.75,
        "Szállítás\/raktározás": 48.5,
        "Mezőgazdaság, bányászat": 75.9090909091,
        "5-9 fő": 58.019047619,
        "20-49 fő": 56.8833333333,
        "10-19 fő": 60.4285714286,
        "50-249 fő": 75.3103448276,
        "Informatikai eszközt használó munkavállalók": null
    },
    {
        "id": "OTP1",
        "max_point": null,
        "average_points": null,
        "Budapest": null,
        "Közép-Dunántúl": null,
        "Pest megye": null,
        "Nyugat-Dunántúl": null,
        "Észak-Magyarország": null,
        "Dél-Alföld": null,
        "Észak-Alföld": null,
        "Dél-Dunántúl": null,
        "Szálláshely szolgálatatás, vendéglátás": null,
        "Építőipar": null,
        "Pénzügyi, biztosítási tevékenység": null,
        "Adminisztratív és szolgáltatást támogató tevékenység": null,
        "Kereskedelem, gépjárműjavítás": null,
        "Ingatlanügyek": null,
        "Feldolgozóipar": null,
        "Információ, kommunikáció": null,
        "Egyéb (közigazgatás, oktatás, egészségügy, szociális ellátás, művészet, egyéb szolgáltatás)": null,
        "Szakmai, tudományos, műszaki tevékenység, könyvelés": null,
        "Villamosenergia-, gáz-, gőzellátás, légkondicionálás, vízellátás": null,
        "Szállítás\/raktározás": null,
        "Mezőgazdaság, bányászat": null,
        "5-9 fő": null,
        "20-49 fő": null,
        "10-19 fő": null,
        "50-249 fő": null,
        "Informatikai eszközt használó munkavállalók": null
    },
    {
        "id": "OTP2",
        "max_point": null,
        "average_points": null,
        "Budapest": null,
        "Közép-Dunántúl": null,
        "Pest megye": null,
        "Nyugat-Dunántúl": null,
        "Észak-Magyarország": null,
        "Dél-Alföld": null,
        "Észak-Alföld": null,
        "Dél-Dunántúl": null,
        "Szálláshely szolgálatatás, vendéglátás": null,
        "Építőipar": null,
        "Pénzügyi, biztosítási tevékenység": null,
        "Adminisztratív és szolgáltatást támogató tevékenység": null,
        "Kereskedelem, gépjárműjavítás": null,
        "Ingatlanügyek": null,
        "Feldolgozóipar": null,
        "Információ, kommunikáció": null,
        "Egyéb (közigazgatás, oktatás, egészségügy, szociális ellátás, művészet, egyéb szolgáltatás)": null,
        "Szakmai, tudományos, műszaki tevékenység, könyvelés": null,
        "Villamosenergia-, gáz-, gőzellátás, légkondicionálás, vízellátás": null,
        "Szállítás\/raktározás": null,
        "Mezőgazdaság, bányászat": null,
        "5-9 fő": null,
        "20-49 fő": null,
        "10-19 fő": null,
        "50-249 fő": null,
        "Informatikai eszközt használó munkavállalók": null
    },
    {
        "id": "Shoptet1",
        "max_point": null,
        "average_points": null,
        "Budapest": null,
        "Közép-Dunántúl": null,
        "Pest megye": null,
        "Nyugat-Dunántúl": null,
        "Észak-Magyarország": null,
        "Dél-Alföld": null,
        "Észak-Alföld": null,
        "Dél-Dunántúl": null,
        "Szálláshely szolgálatatás, vendéglátás": null,
        "Építőipar": null,
        "Pénzügyi, biztosítási tevékenység": null,
        "Adminisztratív és szolgáltatást támogató tevékenység": null,
        "Kereskedelem, gépjárműjavítás": null,
        "Ingatlanügyek": null,
        "Feldolgozóipar": null,
        "Információ, kommunikáció": null,
        "Egyéb (közigazgatás, oktatás, egészségügy, szociális ellátás, művészet, egyéb szolgáltatás)": null,
        "Szakmai, tudományos, műszaki tevékenység, könyvelés": null,
        "Villamosenergia-, gáz-, gőzellátás, légkondicionálás, vízellátás": null,
        "Szállítás\/raktározás": null,
        "Mezőgazdaság, bányászat": null,
        "5-9 fő": null,
        "20-49 fő": null,
        "10-19 fő": null,
        "50-249 fő": null,
        "Informatikai eszközt használó munkavállalók": null
    },
    {
        "id": "Shoptet2",
        "max_point": null,
        "average_points": null,
        "Budapest": null,
        "Közép-Dunántúl": null,
        "Pest megye": null,
        "Nyugat-Dunántúl": null,
        "Észak-Magyarország": null,
        "Dél-Alföld": null,
        "Észak-Alföld": null,
        "Dél-Dunántúl": null,
        "Szálláshely szolgálatatás, vendéglátás": null,
        "Építőipar": null,
        "Pénzügyi, biztosítási tevékenység": null,
        "Adminisztratív és szolgáltatást támogató tevékenység": null,
        "Kereskedelem, gépjárműjavítás": null,
        "Ingatlanügyek": null,
        "Feldolgozóipar": null,
        "Információ, kommunikáció": null,
        "Egyéb (közigazgatás, oktatás, egészségügy, szociális ellátás, művészet, egyéb szolgáltatás)": null,
        "Szakmai, tudományos, műszaki tevékenység, könyvelés": null,
        "Villamosenergia-, gáz-, gőzellátás, légkondicionálás, vízellátás": null,
        "Szállítás\/raktározás": null,
        "Mezőgazdaság, bányászat": null,
        "5-9 fő": null,
        "20-49 fő": null,
        "10-19 fő": null,
        "50-249 fő": null,
        "Informatikai eszközt használó munkavállalók": null
    },
    {
        "id": "Shoptet3",
        "max_point": null,
        "average_points": null,
        "Budapest": null,
        "Közép-Dunántúl": null,
        "Pest megye": null,
        "Nyugat-Dunántúl": null,
        "Észak-Magyarország": null,
        "Dél-Alföld": null,
        "Észak-Alföld": null,
        "Dél-Dunántúl": null,
        "Szálláshely szolgálatatás, vendéglátás": null,
        "Építőipar": null,
        "Pénzügyi, biztosítási tevékenység": null,
        "Adminisztratív és szolgáltatást támogató tevékenység": null,
        "Kereskedelem, gépjárműjavítás": null,
        "Ingatlanügyek": null,
        "Feldolgozóipar": null,
        "Információ, kommunikáció": null,
        "Egyéb (közigazgatás, oktatás, egészségügy, szociális ellátás, művészet, egyéb szolgáltatás)": null,
        "Szakmai, tudományos, műszaki tevékenység, könyvelés": null,
        "Villamosenergia-, gáz-, gőzellátás, légkondicionálás, vízellátás": null,
        "Szállítás\/raktározás": null,
        "Mezőgazdaság, bányászat": null,
        "5-9 fő": null,
        "20-49 fő": null,
        "10-19 fő": null,
        "50-249 fő": null,
        "Informatikai eszközt használó munkavállalók": null
    },
    {
        "id": "Shoptet4",
        "max_point": null,
        "average_points": null,
        "Budapest": null,
        "Közép-Dunántúl": null,
        "Pest megye": null,
        "Nyugat-Dunántúl": null,
        "Észak-Magyarország": null,
        "Dél-Alföld": null,
        "Észak-Alföld": null,
        "Dél-Dunántúl": null,
        "Szálláshely szolgálatatás, vendéglátás": null,
        "Építőipar": null,
        "Pénzügyi, biztosítási tevékenység": null,
        "Adminisztratív és szolgáltatást támogató tevékenység": null,
        "Kereskedelem, gépjárműjavítás": null,
        "Ingatlanügyek": null,
        "Feldolgozóipar": null,
        "Információ, kommunikáció": null,
        "Egyéb (közigazgatás, oktatás, egészségügy, szociális ellátás, művészet, egyéb szolgáltatás)": null,
        "Szakmai, tudományos, műszaki tevékenység, könyvelés": null,
        "Villamosenergia-, gáz-, gőzellátás, légkondicionálás, vízellátás": null,
        "Szállítás\/raktározás": null,
        "Mezőgazdaság, bányászat": null,
        "5-9 fő": null,
        "20-49 fő": null,
        "10-19 fő": null,
        "50-249 fő": null,
        "Informatikai eszközt használó munkavállalók": null
    },
    {
        "id": "DIGITÁLIS_JELENLÉT",
        "max_point": 100.0,
        "average_points": 39.4900332226,
        "Budapest": 46.6725146199,
        "Közép-Dunántúl": 35.0740740741,
        "Pest megye": 39.512605042,
        "Nyugat-Dunántúl": 37.8076923077,
        "Észak-Magyarország": 33.7073170732,
        "Dél-Alföld": 35.7846153846,
        "Észak-Alföld": 34.95,
        "Dél-Dunántúl": 35.625,
        "Szálláshely szolgálatatás, vendéglátás": 53.3783783784,
        "Építőipar": 29.0384615385,
        "Pénzügyi, biztosítási tevékenység": 27.0,
        "Adminisztratív és szolgáltatást támogató tevékenység": 42.2162162162,
        "Kereskedelem, gépjárműjavítás": 43.3223684211,
        "Ingatlanügyek": 37.1666666667,
        "Feldolgozóipar": 34.7142857143,
        "Információ, kommunikáció": 62.0,
        "Egyéb (közigazgatás, oktatás, egészségügy, szociális ellátás, művészet, egyéb szolgáltatás)": 46.0330578512,
        "Szakmai, tudományos, műszaki tevékenység, könyvelés": 32.6666666667,
        "Villamosenergia-, gáz-, gőzellátás, légkondicionálás, vízellátás": 35.1111111111,
        "Szállítás\/raktározás": 28.25,
        "Mezőgazdaság, bányászat": 29.1304347826,
        "5-9 fő": 34.7115987461,
        "20-49 fő": 45.9418604651,
        "10-19 fő": 43.5316455696,
        "50-249 fő": 47.9743589744,
        "Informatikai eszközt használó munkavállalók": null
    },
    {
        "id": "DIGITÁLIS_MINDENNAPOK",
        "max_point": 100.0,
        "average_points": 41.4784053156,
        "Budapest": 51.6023391813,
        "Közép-Dunántúl": 31.4444444444,
        "Pest megye": 42.2773109244,
        "Nyugat-Dunántúl": 43.3461538462,
        "Észak-Magyarország": 32.243902439,
        "Dél-Alföld": 35.7384615385,
        "Észak-Alföld": 36.2166666667,
        "Dél-Dunántúl": 33.625,
        "Szálláshely szolgálatatás, vendéglátás": 32.2432432432,
        "Építőipar": 35.1346153846,
        "Pénzügyi, biztosítási tevékenység": 55.6153846154,
        "Adminisztratív és szolgáltatást támogató tevékenység": 49.0810810811,
        "Kereskedelem, gépjárműjavítás": 41.0789473684,
        "Ingatlanügyek": 40.1666666667,
        "Feldolgozóipar": 39.5873015873,
        "Információ, kommunikáció": 66.5,
        "Egyéb (közigazgatás, oktatás, egészségügy, szociális ellátás, művészet, egyéb szolgáltatás)": 46.8181818182,
        "Szakmai, tudományos, műszaki tevékenység, könyvelés": 51.6666666667,
        "Villamosenergia-, gáz-, gőzellátás, légkondicionálás, vízellátás": 43.0,
        "Szállítás\/raktározás": 36.375,
        "Mezőgazdaság, bányászat": 34.652173913,
        "5-9 fő": 36.2288401254,
        "20-49 fő": 47.5348837209,
        "10-19 fő": 44.3544303797,
        "50-249 fő": 59.4102564103,
        "Informatikai eszközt használó munkavállalók": null
    },
    {
        "id": "VÁLLALKOZÁSVEZETÉS",
        "max_point": 100.0,
        "average_points": 36.2674418605,
        "Budapest": 39.5321637427,
        "Közép-Dunántúl": 29.3518518519,
        "Pest megye": 36.8907563025,
        "Nyugat-Dunántúl": 38.4230769231,
        "Észak-Magyarország": 34.3414634146,
        "Dél-Alföld": 34.2615384615,
        "Észak-Alföld": 35.7333333333,
        "Dél-Dunántúl": 33.025,
        "Szálláshely szolgálatatás, vendéglátás": 29.1081081081,
        "Építőipar": 32.5480769231,
        "Pénzügyi, biztosítási tevékenység": 41.2307692308,
        "Adminisztratív és szolgáltatást támogató tevékenység": 36.7567567568,
        "Kereskedelem, gépjárműjavítás": 39.0789473684,
        "Ingatlanügyek": 42.6666666667,
        "Feldolgozóipar": 37.5873015873,
        "Információ, kommunikáció": 42.5,
        "Egyéb (közigazgatás, oktatás, egészségügy, szociális ellátás, művészet, egyéb szolgáltatás)": 36.867768595,
        "Szakmai, tudományos, műszaki tevékenység, könyvelés": 34.8666666667,
        "Villamosenergia-, gáz-, gőzellátás, légkondicionálás, vízellátás": 41.5555555556,
        "Szállítás\/raktározás": 30.875,
        "Mezőgazdaság, bányászat": 34.9565217391,
        "5-9 fő": 31.5141065831,
        "20-49 fő": 43.1976744186,
        "10-19 fő": 38.0506329114,
        "50-249 fő": 52.641025641,
        "Informatikai eszközt használó munkavállalók": null
    },
    {
        "id": "ÉRTÉKESÍTÉS_ÉS_MARKETING",
        "max_point": 195.0,
        "average_points": 14.4551495017,
        "Budapest": 16.5847953216,
        "Közép-Dunántúl": 10.0648148148,
        "Pest megye": 15.2394957983,
        "Nyugat-Dunántúl": 13.0288461538,
        "Észak-Magyarország": 13.0609756098,
        "Dél-Alföld": 12.4538461538,
        "Észak-Alföld": 15.0333333333,
        "Dél-Dunántúl": 14.6125,
        "Szálláshely szolgálatatás, vendéglátás": 19.0135135135,
        "Építőipar": 9.5625,
        "Pénzügyi, biztosítási tevékenység": 9.0384615385,
        "Adminisztratív és szolgáltatást támogató tevékenység": 12.1621621622,
        "Kereskedelem, gépjárműjavítás": 19.625,
        "Ingatlanügyek": 11.5833333333,
        "Feldolgozóipar": 13.873015873,
        "Információ, kommunikáció": 27.6666666667,
        "Egyéb (közigazgatás, oktatás, egészségügy, szociális ellátás, művészet, egyéb szolgáltatás)": 13.7272727273,
        "Szakmai, tudományos, műszaki tevékenység, könyvelés": 6.5,
        "Villamosenergia-, gáz-, gőzellátás, légkondicionálás, vízellátás": 15.2777777778,
        "Szállítás\/raktározás": 9.3125,
        "Mezőgazdaság, bányászat": 13.0,
        "5-9 fő": 11.6598746082,
        "20-49 fő": 18.3546511628,
        "10-19 fő": 16.7594936709,
        "50-249 fő": 19.3846153846,
        "Informatikai eszközt használó munkavállalók": null
    },
    {
        "id": "DIGITÁLIS_PÉNZÜGYEK",
        "max_point": 100.0,
        "average_points": 65.0149501661,
        "Budapest": 66.2573099415,
        "Közép-Dunántúl": 60.5740740741,
        "Pest megye": 67.2268907563,
        "Nyugat-Dunántúl": 66.1153846154,
        "Észak-Magyarország": 68.2682926829,
        "Dél-Alföld": 60.4307692308,
        "Észak-Alföld": 65.2833333333,
        "Dél-Dunántúl": 61.4,
        "Szálláshely szolgálatatás, vendéglátás": 62.9189189189,
        "Építőipar": 63.9615384615,
        "Pénzügyi, biztosítási tevékenység": 77.6153846154,
        "Adminisztratív és szolgáltatást támogató tevékenység": 66.8648648649,
        "Kereskedelem, gépjárműjavítás": 63.6710526316,
        "Ingatlanügyek": 56.1666666667,
        "Feldolgozóipar": 68.6031746032,
        "Információ, kommunikáció": 68.5,
        "Egyéb (közigazgatás, oktatás, egészségügy, szociális ellátás, művészet, egyéb szolgáltatás)": 64.5537190083,
        "Szakmai, tudományos, műszaki tevékenység, könyvelés": 74.0,
        "Villamosenergia-, gáz-, gőzellátás, légkondicionálás, vízellátás": 73.6666666667,
        "Szállítás\/raktározás": 63.3125,
        "Mezőgazdaság, bányászat": 57.8695652174,
        "5-9 fő": 62.8996865204,
        "20-49 fő": 69.1162790698,
        "10-19 fő": 65.8860759494,
        "50-249 fő": 69.7435897436,
        "Informatikai eszközt használó munkavállalók": null
    },
    {
        "id": "INFORMATIKAI_BIZTONSÁG",
        "max_point": 100.0,
        "average_points": 53.5531561462,
        "Budapest": 60.6725146199,
        "Közép-Dunántúl": 44.1481481481,
        "Pest megye": 54.4369747899,
        "Nyugat-Dunántúl": 56.1730769231,
        "Észak-Magyarország": 51.5853658537,
        "Dél-Alföld": 49.3538461538,
        "Észak-Alföld": 48.55,
        "Dél-Dunántúl": 46.125,
        "Szálláshely szolgálatatás, vendéglátás": 48.8378378378,
        "Építőipar": 45.5096153846,
        "Pénzügyi, biztosítási tevékenység": 68.2307692308,
        "Adminisztratív és szolgáltatást támogató tevékenység": 58.2702702703,
        "Kereskedelem, gépjárműjavítás": 55.3026315789,
        "Ingatlanügyek": 56.8333333333,
        "Feldolgozóipar": 51.5555555556,
        "Információ, kommunikáció": 63.6666666667,
        "Egyéb (közigazgatás, oktatás, egészségügy, szociális ellátás, művészet, egyéb szolgáltatás)": 58.652892562,
        "Szakmai, tudományos, műszaki tevékenység, könyvelés": 54.4,
        "Villamosenergia-, gáz-, gőzellátás, légkondicionálás, vízellátás": 59.4444444444,
        "Szállítás\/raktározás": 47.0625,
        "Mezőgazdaság, bányászat": 46.8695652174,
        "5-9 fő": 47.4231974922,
        "20-49 fő": 59.7325581395,
        "10-19 fő": 58.5,
        "50-249 fő": 70.0256410256,
        "Informatikai eszközt használó munkavállalók": null
    },
    {
        "id": "DIGIMÉTER_INDEX",
        "max_point": 100.0,
        "average_points": 40.2265116279,
        "Budapest": 45.423625731,
        "Közép-Dunántúl": 33.7952777778,
        "Pest megye": 41.0824789916,
        "Nyugat-Dunántúl": 40.7999038462,
        "Észak-Magyarország": 37.1042682927,
        "Dél-Alföld": 36.5353076923,
        "Észak-Alföld": 37.8811666667,
        "Dél-Dunántúl": 36.115625,
        "Szálláshely szolgálatatás, vendéglátás": 39.9771621622,
        "Építőipar": 34.4573557692,
        "Pénzügyi, biztosítási tevékenység": 43.935,
        "Adminisztratív és szolgáltatást támogató tevékenység": 42.6464864865,
        "Kereskedelem, gépjárműjavítás": 42.2882894737,
        "Ingatlanügyek": 38.9591666667,
        "Feldolgozóipar": 39.4147619048,
        "Információ, kommunikáció": 54.435,
        "Egyéb (közigazgatás, oktatás, egészségügy, szociális ellátás, művészet, egyéb szolgáltatás)": 42.9291735537,
        "Szakmai, tudományos, műszaki tevékenység, könyvelés": 40.661,
        "Villamosenergia-, gáz-, gőzellátás, légkondicionálás, vízellátás": 42.7183333333,
        "Szállítás\/raktározás": 34.295,
        "Mezőgazdaság, bányászat": 34.5965217391,
        "5-9 fő": 36.0168181818,
        "20-49 fő": 45.7887790698,
        "10-19 fő": 42.9475316456,
        "50-249 fő": 51.3705128205,
        "Informatikai eszközt használó munkavállalók": null
    },
    {
        "id": "INDEX_egyenloarany",
        "max_point": 100.0,
        "average_points": 41.7098560354,
        "Budapest": 46.8869395712,
        "Közép-Dunántúl": 35.1095679012,
        "Pest megye": 42.5973389356,
        "Nyugat-Dunántúl": 42.4823717949,
        "Észak-Magyarország": 38.8678861789,
        "Dél-Alföld": 38.0038461538,
        "Észak-Alföld": 39.2944444444,
        "Dél-Dunántúl": 37.4020833333,
        "Szálláshely szolgálatatás, vendéglátás": 40.9166666667,
        "Építőipar": 35.9591346154,
        "Pénzügyi, biztosítási tevékenység": 46.4551282051,
        "Adminisztratív és szolgáltatást támogató tevékenység": 44.2252252252,
        "Kereskedelem, gépjárműjavítás": 43.6798245614,
        "Ingatlanügyek": 40.7638888889,
        "Feldolgozóipar": 40.9867724868,
        "Információ, kommunikáció": 55.1388888889,
        "Egyéb (közigazgatás, oktatás, egészségügy, szociális ellátás, művészet, egyéb szolgáltatás)": 44.4421487603,
        "Szakmai, tudományos, műszaki tevékenység, könyvelés": 42.35,
        "Villamosenergia-, gáz-, gőzellátás, légkondicionálás, vízellátás": 44.6759259259,
        "Szállítás\/raktározás": 35.8645833333,
        "Mezőgazdaság, bányászat": 36.0797101449,
        "5-9 fő": 37.4062173459,
        "20-49 fő": 47.3129844961,
        "10-19 fő": 44.5137130802,
        "50-249 fő": 53.1965811966,
        "Informatikai eszközt használó munkavállalók": null
    }
]